[{"brand": "Tennent Caledonian Breweries", "name": "Tennents Export Lager", "alcohol": 5.0, "pictureLink": "http://www.thebeerstore.ca/sites/default/files/styles/brand_hero/public/sbs/brand/2086H.jpg?itok=IfGfEpfu", "pageLink": "http://www.thebeerstore.ca/beers/tennents-export-lager", "rank": 0, "main": 0, "info": [["Can", 500, 24, 58.75, 1, 49.95, 18.682235195996665, 246.15385, 12.30769], ["Can", 500, 6, 14.649999999999999, 0, 0, 0, 204.77816, 10.23891], ["Can", 500, 12, 29.349999999999998, 0, 0, 0, 204.4293, 10.22147], ["Can", 500, 1, 2.8, 0, 0, 0, 181.81818, 9.09091]], "cnt": 4, "salePercent": 18.682235195996665, "value": 246.15385, "valAlc": 12.30769, "isSale": true, "price": 58.75}, {"brand": "Diageo", "name": "Harp Lager", "alcohol": 5.0, "pictureLink": "http://www.thebeerstore.ca/sites/default/files/styles/brand_hero/public/brand/hero/2024-l.jpg?itok=jWblTts9", "pageLink": "http://www.thebeerstore.ca/beers/harp-lager", "rank": 1, "main": 0, "info": [["Can", 500, 1, 2.45, 1, 2.05, 16.326530612244916, 250.0, 12.5], ["Can", 500, 24, 53.949999999999996, 0, 0, 0, 222.42817, 11.12141]], "cnt": 2, "salePercent": 16.326530612244916, "value": 250.0, "valAlc": 12.5, "isSale": true, "price": 2.45}, {"brand": "Carlsberg International A/S", "name": "Carlsberg", "alcohol": 5.0, "pictureLink": "http://www.thebeerstore.ca/sites/default/files/styles/brand_hero/public/sbs/brand/2129%20H.png?itok=gLxC8bhk", "pageLink": "http://www.thebeerstore.ca/beers/carlsberg", "rank": 2, "main": 0, "info": [["Can", 500, 24, 52.75, 0, 0, 0, 227.48815, 11.37441], ["Can", 500, 1, 2.35, 1, 2.3, 2.1276595744680993, 222.22222, 11.11111], ["Bottle", 330, 24, 43.550000000000004, 1, 41.1, 15.778019586507074, 204.65116, 10.23256], ["Can", 330, 24, 44.75, 0, 0, 0, 176.98324, 8.84916], ["Bottle", 330, 12, 24.2, 0, 0, 0, 163.63636, 8.18182], ["Bottle", 330, 6, 12.4, 1, 12.9, 5.384615384615376, 160.97561, 8.04878], ["Can", 330, 6, 12.799999999999999, 0, 0, 0, 154.6875, 7.73438]], "cnt": 7, "salePercent": 15.778019586507074, "value": 227.48815, "valAlc": 11.37441, "isSale": true, "price": 52.75}, {"brand": "Pilsner Urquell A.S.", "name": "Pilsner Urquell", "alcohol": 4.0, "pictureLink": "http://www.thebeerstore.ca/sites/default/files/styles/brand_hero/public/brand/hero/grolsch.jpg?itok=-Z6VMuXq", "pageLink": "http://www.thebeerstore.ca/beers/pilsner-urquell", "rank": 3, "main": 0, "info": [["Can", 500, 24, 58.75, 0, 0, 0, 204.25532, 8.17021], ["Can", 500, 4, 10.55, 0, 0, 0, 189.57346, 7.58294], ["Can", 500, 1, 2.9, 0, 0, 0, 175.4386, 7.01754], ["Bottle", 330, 24, 46.550000000000004, 0, 0, 0, 170.13963, 6.80559], ["Bottle", 330, 6, 13.55, 1, 12.65, 14.840989399293282, 164.31535, 6.57261], ["Bottle", 330, 12, 25.75, 0, 0, 0, 153.78641, 6.15146]], "cnt": 6, "salePercent": 14.840989399293282, "value": 204.25532, "valAlc": 8.17021, "isSale": true, "price": 58.75}, {"brand": "Flying Monkeys Craft Brewery", "name": "Flying Monkeys Hoptical", "alcohol": 5.0, "pictureLink": "http://www.thebeerstore.ca/sites/default/files/styles/brand_hero/public/sbs/brand/1612H.png?itok=lylUj9xx", "pageLink": "http://www.thebeerstore.ca/beers/flying-monkeys-hoptical", "rank": 4, "main": 0, "info": [["Bottle", 355, 24, 47.550000000000004, 1, 44.95, 14.814814814814813, 200.23502, 10.01175], ["Can", 473, 24, 65.75, 0, 0, 0, 172.65399, 8.6327], ["Bottle", 355, 12, 25.3, 0, 0, 0, 168.37945, 8.41897], ["Can", 473, 8, 23.55, 0, 0, 0, 160.67941, 8.03397], ["Bottle", 355, 6, 13.35, 0, 0, 0, 159.55056, 7.97753], ["Can", 473, 1, 3.15, 0, 0, 0, 152.58065, 7.62903]], "cnt": 6, "salePercent": 14.814814814814813, "value": 200.23502, "valAlc": 10.01175, "isSale": true, "price": 47.550000000000004}, {"brand": "Bitburger Braugruppe GMBh", "name": "Bitburger", "alcohol": 4.0, "pictureLink": "http://www.thebeerstore.ca/sites/default/files/styles/brand_hero/public/sbs/brand/2182H.png?itok=F1svGXtF", "pageLink": "http://www.thebeerstore.ca/beers/bitburger", "rank": 5, "main": 0, "info": [["Can", 500, 1, 2.5, 1, 2.15, 14.000000000000002, 238.09524, 9.52381], ["Bottle", 355, 6, 12.3, 0, 0, 0, 173.17073, 6.92683]], "cnt": 2, "salePercent": 14.000000000000002, "value": 238.09524, "valAlc": 9.52381, "isSale": true, "price": 2.5}, {"brand": "Bavaria", "name": "Bavaria Premium Beer", "alcohol": 5.0, "pictureLink": "http://www.thebeerstore.ca/sites/default/files/styles/brand_hero/public/sbs/brand/Bavaria-TBS%20can%20and%20glass.jpg?itok=pO57Rw2s", "pageLink": "http://www.thebeerstore.ca/beers/bavaria-holland-beer", "rank": 6, "main": 0, "info": [["Can", 440, 24, 41.75, 0, 0, 0, 252.93413, 12.64671], ["Can", 440, 6, 10.7, 0, 0, 0, 246.72897, 12.33645], ["Can", 440, 1, 2.0, 0, 0, 0, 225.64103, 11.28205], ["Bottle", 330, 12, 21.75, 1, 20.95, 13.943355119825707, 200.50633, 10.02532], ["Bottle", 330, 24, 42.550000000000004, 0, 0, 0, 186.13396, 9.3067]], "cnt": 5, "salePercent": 13.943355119825707, "value": 252.93413, "valAlc": 12.64671, "isSale": true, "price": 41.75}, {"brand": "Carlsberg International A/S", "name": "Kronenbourg 1664 Blanc", "alcohol": 5.0, "pictureLink": "http://www.thebeerstore.ca/sites/default/files/styles/brand_hero/public/brand/hero/1664-blanc_0.jpg?itok=20l7XPvu", "pageLink": "http://www.thebeerstore.ca/beers/kronenbourg-1664-blanc", "rank": 7, "main": 0, "info": [["Can", 500, 24, 57.75, 0, 0, 0, 207.79221, 10.38961], ["Can", 500, 1, 2.85, 1, 2.5, 12.28070175438597, 204.08163, 10.20408], ["Bottle", 330, 24, 44.550000000000004, 1, 42.9, 13.738019169329075, 195.55556, 9.77778], ["Can", 330, 24, 45.75, 0, 0, 0, 173.11475, 8.65574], ["Bottle", 330, 12, 24.3, 0, 0, 0, 162.96296, 8.14815], ["Can", 330, 12, 24.9, 0, 0, 0, 159.03614, 7.95181], ["Bottle", 330, 6, 13.5, 0, 0, 0, 146.66667, 7.33333], ["Can", 330, 6, 13.7, 0, 0, 0, 144.52555, 7.22628]], "cnt": 8, "salePercent": 13.738019169329075, "value": 207.79221, "valAlc": 10.38961, "isSale": true, "price": 57.75}, {"brand": "Sleeman Brewing", "name": "Sleeman Clear 2.0", "alcohol": 4.0, "pictureLink": "http://www.thebeerstore.ca/sites/default/files/styles/brand_hero/public/brand/hero/SCR%20beer-glass-RGB.jpg?itok=ElyT8osw", "pageLink": "http://www.thebeerstore.ca/beers/sleeman-clear-20", "rank": 8, "main": 0, "info": [["Bottle", 341, 30, 42.95, 0, 0, 0, 238.18393, 9.52736], ["Bottle", 341, 24, 34.550000000000004, 0, 0, 0, 236.8741, 9.47496], ["Bottle", 341, 15, 24.5, 1, 23.95, 13.65384615384616, 227.83964, 9.11359], ["Can", 473, 24, 52.75, 0, 0, 0, 215.20379, 8.60815], ["Can", 473, 12, 27.349999999999998, 0, 0, 0, 207.53199, 8.30128], ["Can", 355, 30, 51.45, 0, 0, 0, 206.99708, 8.27988], ["Keg", 30000, 1, 146.25, 0, 0, 0, 205.12821, 8.20513], ["Can", 355, 24, 41.75, 0, 0, 0, 204.07186, 8.16287], ["Can", 355, 15, 26.2, 0, 0, 0, 203.24427, 8.12977], ["Can", 473, 6, 14.2, 0, 0, 0, 199.85915, 7.99437], ["Can", 473, 4, 9.75, 0, 0, 0, 194.05128, 7.76205], ["Can", 473, 2, 4.9, 0, 0, 0, 193.06122, 7.72245], ["Can", 473, 1, 2.55, 0, 0, 0, 189.2, 7.568], ["Bottle", 341, 12, 22.75, 0, 0, 0, 179.86813, 7.19473], ["Can", 355, 12, 26.349999999999998, 0, 0, 0, 161.66983, 6.46679]], "cnt": 15, "salePercent": 13.65384615384616, "value": 238.18393, "valAlc": 9.52736, "isSale": true, "price": 42.95}, {"brand": "Sleeman Brewing", "name": "Sleeman Orig. Draught", "alcohol": 5.0, "pictureLink": "http://www.thebeerstore.ca/sites/default/files/styles/brand_hero/public/brand/hero/SDR%20beer-glass-RGB.jpg?itok=enm4JnkZ", "pageLink": "http://www.thebeerstore.ca/beers/sleeman-original-draught", "rank": 9, "main": 0, "info": [["Bottle", 341, 30, 42.95, 0, 0, 0, 238.18393, 11.9092], ["Bottle", 341, 24, 34.550000000000004, 0, 0, 0, 236.8741, 11.8437], ["Bottle", 341, 15, 24.5, 1, 23.95, 13.65384615384616, 227.83964, 11.39198], ["Can", 473, 6, 14.2, 1, 13.25, 10.689655172413804, 219.15058, 10.95753], ["Can", 473, 24, 52.75, 0, 0, 0, 215.20379, 10.76019], ["Can", 473, 12, 27.349999999999998, 0, 0, 0, 207.53199, 10.3766], ["Can", 355, 30, 51.45, 0, 0, 0, 206.99708, 10.34985], ["Keg", 58600, 1, 285.2, 0, 0, 0, 205.46985, 10.27349], ["Keg", 30000, 1, 146.25, 0, 0, 0, 205.12821, 10.25641], ["Can", 355, 15, 26.2, 0, 0, 0, 203.24427, 10.16221], ["Can", 473, 4, 9.75, 0, 0, 0, 194.05128, 9.70256], ["Can", 473, 2, 4.9, 0, 0, 0, 193.06122, 9.65306], ["Can", 473, 1, 2.55, 0, 0, 0, 189.2, 9.46], ["Bottle", 341, 12, 22.75, 0, 0, 0, 179.86813, 8.99341]], "cnt": 14, "salePercent": 13.65384615384616, "value": 238.18393, "valAlc": 11.9092, "isSale": true, "price": 42.95}, {"brand": "Boston Beer Company", "name": "Samuel Adams Boston Lager", "alcohol": 4.0, "pictureLink": "http://www.thebeerstore.ca/sites/default/files/styles/brand_hero/public/sbs/brand/2063H.png?itok=SqM6vQFL", "pageLink": "http://www.thebeerstore.ca/beers/samuel-adams-boston-lager", "rank": 10, "main": 0, "info": [["Bottle", 355, 24, 46.1, 1, 44.5, 13.195876288659791, 202.3753, 8.09501], ["Can", 473, 24, 62.75, 0, 0, 0, 180.90837, 7.23633], ["Can", 473, 12, 33.6, 0, 0, 0, 168.92857, 6.75714], ["Can", 473, 6, 16.95, 0, 0, 0, 167.43363, 6.69735], ["Bottle", 355, 12, 25.8, 0, 0, 0, 165.11628, 6.60465], ["Can", 473, 1, 3.1, 0, 0, 0, 155.08197, 6.20328], ["Bottle", 355, 6, 13.85, 0, 0, 0, 153.79061, 6.15162]], "cnt": 7, "salePercent": 13.195876288659791, "value": 202.3753, "valAlc": 8.09501, "isSale": true, "price": 46.1}, {"brand": "Big Rock Brewery", "name": "Big Rock Variety Pack", "alcohol": 5.0, "pictureLink": "http://www.thebeerstore.ca/sites/default/files/styles/brand_hero/public/sbs/brand/955H.png?itok=QKTLqVky", "pageLink": "http://www.thebeerstore.ca/beers/big-rock-variety-pack", "rank": 11, "main": 0, "info": [["Bottle", 330, 24, 51.1, 1, 49.5, 11.962616822429906, 168.15287, 8.40764], ["Bottle", 330, 12, 27.0, 1, 25.0, 7.4074074074074066, 166.38655, 8.31933]], "cnt": 2, "salePercent": 11.962616822429906, "value": 168.15287, "valAlc": 8.40764, "isSale": true, "price": 51.1}, {"brand": "Abro Bryggeri", "name": "Brygg Mastarens Organic", "alcohol": 5.0, "pictureLink": "http://www.thebeerstore.ca/sites/default/files/styles/brand_hero/public/sbs/brand/2508H.jpg?itok=-HIblSdp", "pageLink": "http://www.thebeerstore.ca/beers/bryg-mastarens-organic", "rank": 12, "main": 0, "info": [["Can", 500, 1, 2.55, 1, 2.25, 11.764705882352933, 227.27273, 11.36364], ["Can", 500, 24, 58.8, 0, 0, 0, 204.08163, 10.20408]], "cnt": 2, "salePercent": 11.764705882352933, "value": 227.27273, "valAlc": 11.36364, "isSale": true, "price": 2.55}, {"brand": "Ab Inbev", "name": "Stella Artois", "alcohol": 5.0, "pictureLink": "http://www.thebeerstore.ca/sites/default/files/styles/brand_hero/public/sbs/brand/TBS_Brand_Lockups_STA.jpg?itok=yB0uJW0J", "pageLink": "http://www.thebeerstore.ca/beers/stella-artois", "rank": 13, "main": 0, "info": [["Can", 500, 24, 60.75, 0, 0, 0, 197.53086, 9.87654], ["Can", 500, 12, 31.349999999999998, 0, 0, 0, 191.38756, 9.56938], ["Can", 500, 8, 21.55, 0, 0, 0, 185.61485, 9.28074], ["Can", 500, 4, 11.05, 0, 0, 0, 180.99548, 9.04977], ["Keg", 12000, 1, 66.75, 0, 0, 0, 179.77528, 8.98876], ["Can", 500, 1, 3.0, 0, 0, 0, 169.49153, 8.47458], ["Bottle", 330, 24, 47.550000000000004, 0, 0, 0, 166.56151, 8.32808], ["Can", 330, 24, 47.75, 0, 0, 0, 165.86387, 8.29319], ["Bottle", 330, 12, 26.3, 1, 25.5, 11.636363636363633, 162.96296, 8.14815], ["Bottle", 330, 6, 13.9, 1, 13.5, 11.03448275862069, 153.48837, 7.67442], ["Can", 330, 12, 25.9, 0, 0, 0, 152.89575, 7.64479], ["Keg", 50000, 1, 327.4, 0, 0, 0, 152.71839, 7.63592], ["Can", 330, 6, 13.649999999999999, 0, 0, 0, 145.05495, 7.25275], ["Keg", 30000, 1, 214.5, 0, 0, 0, 139.86014, 6.99301]], "cnt": 14, "salePercent": 11.636363636363633, "value": 197.53086, "valAlc": 9.87654, "isSale": true, "price": 60.75}, {"brand": "Heineken Brouwerijen BV", "name": "Heineken", "alcohol": 5.0, "pictureLink": "http://www.thebeerstore.ca/sites/default/files/styles/brand_hero/public/brand/hero/heineken.jpg?itok=bORtwyPr", "pageLink": "http://www.thebeerstore.ca/beers/heineken-nv", "rank": 14, "main": 0, "info": [["Can", 500, 24, 60.75, 0, 0, 0, 197.53086, 9.87654], ["Bottle", 650, 12, 40.3, 0, 0, 0, 193.54839, 9.67742], ["Can", 500, 12, 31.349999999999998, 0, 0, 0, 191.38756, 9.56938], ["Can", 500, 8, 21.55, 0, 0, 0, 185.61485, 9.28074], ["Bottle", 330, 24, 43.550000000000004, 0, 0, 0, 181.85993, 9.093], ["Can", 500, 4, 11.05, 0, 0, 0, 180.99548, 9.04977], ["Can", 710, 1, 3.95, 0, 0, 0, 179.74684, 8.98734], ["Can", 500, 1, 3.0, 0, 0, 0, 169.49153, 8.47458], ["Can", 330, 24, 46.75, 0, 0, 0, 169.41176, 8.47059], ["Can", 5000, 2, 59.9, 0, 0, 0, 166.94491, 8.34725], ["Bottle", 650, 1, 3.9, 0, 0, 0, 166.66667, 8.33333], ["Bottle", 330, 18, 35.7, 0, 0, 0, 166.38655, 8.31933], ["Can", 5000, 1, 31.45, 0, 0, 0, 158.98251, 7.94913], ["Keg", 50000, 1, 320.0, 0, 0, 0, 156.25, 7.8125], ["Can", 330, 12, 25.349999999999998, 0, 0, 0, 156.21302, 7.81065], ["Bottle", 330, 6, 13.9, 1, 13.5, 11.03448275862069, 153.48837, 7.67442], ["Bottle", 330, 12, 26.3, 0, 0, 0, 150.57034, 7.52852], ["Can", 330, 6, 13.45, 0, 0, 0, 147.2119, 7.36059]], "cnt": 18, "salePercent": 11.03448275862069, "value": 197.53086, "valAlc": 9.87654, "isSale": true, "price": 60.75}, {"brand": "Moosehead Breweries Limited", "name": "Moosehead Lager", "alcohol": 5.0, "pictureLink": "http://www.thebeerstore.ca/sites/default/files/styles/brand_hero/public/sbs/brand/7351H.png?itok=ztFLFoHk", "pageLink": "http://www.thebeerstore.ca/beers/moosehead-lager", "rank": 15, "main": 0, "info": [["Bottle", 341, 28, 40.7, 0, 0, 0, 234.59459, 11.72973], ["Bottle", 341, 24, 37.550000000000004, 1, 37.95, 11.01376720901126, 230.21097, 11.51055], ["Bottle", 341, 18, 29.15, 0, 0, 0, 210.56604, 10.5283], ["Can", 473, 24, 56.75, 0, 0, 0, 200.03524, 10.00176], ["Can", 473, 12, 29.349999999999998, 0, 0, 0, 193.39012, 9.66951], ["Can", 473, 4, 10.3, 0, 0, 0, 183.68932, 9.18447], ["Can", 473, 1, 2.65, 0, 0, 0, 181.92308, 9.09615], ["Can", 355, 24, 47.75, 0, 0, 0, 178.42932, 8.92147], ["Can", 355, 18, 37.6, 0, 0, 0, 169.94681, 8.49734], ["Bottle", 341, 12, 24.75, 0, 0, 0, 165.33333, 8.26667], ["Bottle", 341, 6, 13.35, 0, 0, 0, 153.25843, 7.66292], ["Can", 355, 12, 28.9, 0, 0, 0, 147.40484, 7.37024]], "cnt": 12, "salePercent": 11.01376720901126, "value": 234.59459, "valAlc": 11.72973, "isSale": true, "price": 40.7}, {"brand": "Carlsberg International A/S", "name": "Kronenbourg 1664", "alcohol": 5.0, "pictureLink": "http://www.thebeerstore.ca/sites/default/files/styles/brand_hero/public/sbs/brand/2119H_1.png?itok=5PNERlXK", "pageLink": "http://www.thebeerstore.ca/beers/kronenbourg-1664", "rank": 16, "main": 0, "info": [["Can", 500, 24, 56.75, 1, 52.95, 10.698878343399487, 231.88406, 11.5942], ["Can", 500, 1, 2.85, 0, 0, 0, 178.57143, 8.92857], ["Bottle", 330, 24, 44.550000000000004, 0, 0, 0, 177.77778, 8.88889], ["Bottle", 330, 12, 26.3, 0, 0, 0, 150.57034, 7.52852], ["Bottle", 330, 6, 13.5, 0, 0, 0, 146.66667, 7.33333]], "cnt": 5, "salePercent": 10.698878343399487, "value": 231.88406, "valAlc": 11.5942, "isSale": true, "price": 56.75}, {"brand": "Pilsner Urquell A.S.", "name": "Kozel", "alcohol": 5.0, "pictureLink": "http://www.thebeerstore.ca/sites/default/files/styles/brand_hero/public/sbs/brand/2136H.png?itok=LwPc52R2", "pageLink": "http://www.thebeerstore.ca/beers/kozel", "rank": 17, "main": 0, "info": [["Can", 500, 24, 46.9, 0, 0, 0, 255.86354, 12.79318], ["Can", 500, 4, 8.15, 0, 0, 0, 245.39877, 12.26994], ["Can", 500, 1, 2.35, 1, 2.1, 10.63829787234043, 243.90244, 12.19512]], "cnt": 3, "salePercent": 10.63829787234043, "value": 255.86354, "valAlc": 12.79318, "isSale": true, "price": 46.9}, {"brand": "Coors Brewery", "name": "Coors Banquet", "alcohol": 5.0, "pictureLink": "http://www.thebeerstore.ca/sites/default/files/styles/brand_hero/public/brand/hero/Banquet_473mL_Can.jpg?itok=jqJAAUYA", "pageLink": "http://www.thebeerstore.ca/beers/coors-banquet", "rank": 18, "main": 0, "info": [["Keg", 58600, 1, 293.95, 0, 0, 0, 199.35363, 9.96768], ["Can", 355, 24, 45.75, 1, 43.95, 8.94568690095847, 199.29825, 9.96491], ["Can", 473, 24, 57.75, 0, 0, 0, 196.57143, 9.82857], ["Can", 473, 12, 29.349999999999998, 0, 0, 0, 193.39012, 9.66951], ["Can", 355, 12, 24.349999999999998, 1, 22.95, 10.420841683366744, 190.60403, 9.5302], ["Can", 473, 6, 15.45, 0, 0, 0, 183.68932, 9.18447], ["Bottle", 355, 24, 46.550000000000004, 0, 0, 0, 183.029, 9.15145], ["Keg", 20000, 1, 109.94999999999999, 0, 0, 0, 181.90086, 9.09504], ["Can", 473, 1, 2.7, 0, 0, 0, 178.49057, 8.92453], ["Bottle", 355, 12, 24.75, 0, 0, 0, 172.12121, 8.60606]], "cnt": 10, "salePercent": 10.420841683366744, "value": 199.35363, "valAlc": 9.96768, "isSale": true, "price": 293.95}, {"brand": "Molson", "name": "Mad Jack", "alcohol": 5.0, "pictureLink": "http://www.thebeerstore.ca/sites/default/files/styles/brand_hero/public/sbs/brand/MADJACK%20ARRAY.JPG?itok=WRxg2cIL", "pageLink": "http://www.thebeerstore.ca/beers/mad-jack", "rank": 19, "main": 0, "info": [["Can", 473, 12, 28.349999999999998, 1, 26.95, 8.981001727115723, 215.40797, 10.7704], ["Can", 473, 24, 56.75, 0, 0, 0, 200.03524, 10.00176], ["Bottle", 341, 24, 42.550000000000004, 0, 0, 0, 192.33843, 9.61692], ["Can", 355, 24, 44.75, 0, 0, 0, 190.39106, 9.51955], ["Can", 473, 6, 14.95, 0, 0, 0, 189.83278, 9.49164], ["Can", 355, 12, 25.349999999999998, 1, 23.95, 10.019267822736033, 182.44111, 9.12206], ["Can", 473, 1, 2.75, 0, 0, 0, 175.18519, 8.75926], ["Bottle", 341, 12, 23.75, 0, 0, 0, 172.29474, 8.61474]], "cnt": 8, "salePercent": 10.019267822736033, "value": 215.40797, "valAlc": 10.7704, "isSale": true, "price": 28.349999999999998}, {"brand": "Diageo", "name": "Guinness Blonde Lager", "alcohol": 5.0, "pictureLink": "http://www.thebeerstore.ca/sites/default/files/styles/brand_hero/public/sbs/brand/GuinnessBlonde_CanPint.jpg?itok=-U9pQBgh", "pageLink": "http://www.thebeerstore.ca/beers/guinness-blonde-american-lager", "rank": 20, "main": 0, "info": [["Can", 473, 1, 2.5, 1, 2.25, 9.999999999999998, 215.0, 10.75], ["Can", 473, 24, 56.75, 0, 0, 0, 200.03524, 10.00176]], "cnt": 2, "salePercent": 9.999999999999998, "value": 215.0, "valAlc": 10.75, "isSale": true, "price": 2.5}, {"brand": "Labatt", "name": "Rolling Rock Pale Lager", "alcohol": 4.0, "pictureLink": "http://www.thebeerstore.ca/sites/default/files/styles/brand_hero/public/sbs/brand/TBS_Brand_Lockups_RR.jpg?itok=JOhzHBDC", "pageLink": "http://www.thebeerstore.ca/beers/rolling-rock-pale-lager", "rank": 21, "main": 0, "info": [["Bottle", 341, 24, 34.6, 1, 35.95, 9.324324324324317, 243.93443, 9.75738], ["Bottle", 341, 28, 42.45, 0, 0, 0, 224.92344, 8.99694], ["Can", 473, 24, 56.75, 0, 0, 0, 200.03524, 8.00141], ["Keg", 58600, 1, 292.95, 0, 0, 0, 200.03414, 8.00137], ["Can", 473, 12, 29.349999999999998, 0, 0, 0, 193.39012, 7.7356], ["Can", 355, 24, 45.8, 0, 0, 0, 186.0262, 7.44105], ["Can", 473, 1, 2.7, 0, 0, 0, 178.49057, 7.13962], ["Bottle", 341, 12, 23.3, 0, 0, 0, 175.62232, 7.02489], ["Keg", 20000, 1, 115.0, 0, 0, 0, 173.91304, 6.95652], ["Can", 355, 12, 25.9, 0, 0, 0, 164.47876, 6.57915]], "cnt": 10, "salePercent": 9.324324324324317, "value": 243.93443, "valAlc": 9.75738, "isSale": true, "price": 34.6}, {"brand": "Muskoka Brewery", "name": "Muskoka Craft Lager", "alcohol": 4.0, "pictureLink": "http://www.thebeerstore.ca/sites/default/files/styles/brand_hero/public/sbs/brand/Craft_Lager-322x344.jpg?itok=I6TrurHO", "pageLink": "http://www.thebeerstore.ca/beers/muskoka-craft-lager", "rank": 22, "main": 0, "info": [["Can", 473, 24, 63.75, 0, 0, 0, 178.07059, 7.12282], ["Bottle", 341, 24, 47.550000000000004, 0, 0, 0, 172.11356, 6.88454], ["Can", 355, 12, 27.349999999999998, 1, 25.95, 9.302325581395355, 168.04734, 6.72189], ["Can", 473, 8, 23.55, 0, 0, 0, 160.67941, 6.42718], ["Bottle", 341, 12, 25.75, 0, 0, 0, 158.91262, 6.3565], ["Can", 355, 24, 54.699999999999996, 0, 0, 0, 155.75868, 6.23035], ["Can", 473, 1, 3.15, 0, 0, 0, 152.58065, 6.10323], ["Bottle", 341, 6, 13.65, 0, 0, 0, 149.89011, 5.9956]], "cnt": 8, "salePercent": 9.302325581395355, "value": 178.07059, "valAlc": 7.12282, "isSale": true, "price": 63.75}, {"brand": "Mill Street Brewery", "name": "Mill St Original Organic", "alcohol": 4.0, "pictureLink": "http://www.thebeerstore.ca/sites/default/files/styles/brand_hero/public/brand/hero/mill%20st%20organic.jpg?itok=RRxpYqN8", "pageLink": "http://www.thebeerstore.ca/beers/mill-st-original-organic", "rank": 23, "main": 0, "info": [["Bottle", 341, 24, 46.550000000000004, 0, 0, 0, 175.81096, 7.03244], ["Can", 473, 24, 65.3, 0, 0, 0, 173.8438, 6.95375], ["Can", 355, 12, 27.349999999999998, 1, 25.95, 9.302325581395355, 168.04734, 6.72189], ["Can", 473, 12, 33.9, 0, 0, 0, 167.43363, 6.69735], ["Can", 355, 24, 51.75, 0, 0, 0, 164.63768, 6.58551], ["Bottle", 341, 12, 25.3, 0, 0, 0, 161.73913, 6.46957], ["Can", 473, 1, 3.15, 0, 0, 0, 152.58065, 6.10323], ["Bottle", 341, 6, 13.65, 0, 0, 0, 149.89011, 5.9956]], "cnt": 8, "salePercent": 9.302325581395355, "value": 175.81096, "valAlc": 7.03244, "isSale": true, "price": 46.550000000000004}, {"brand": "G A Miller", "name": "Miller Lite", "alcohol": 4.0, "pictureLink": "http://www.thebeerstore.ca/sites/default/files/styles/brand_hero/public/sbs/brand/ML%20Can%20with%20Glass.jpg?itok=gwcW__lB", "pageLink": "http://www.thebeerstore.ca/beers/miller-lite", "rank": 24, "main": 0, "info": [["Bottle", 355, 48, 70.60000000000001, 0, 0, 0, 241.35977, 9.65439], ["Bottle", 355, 24, 35.550000000000004, 0, 0, 0, 239.66245, 9.5865], ["Can", 473, 24, 51.75, 0, 0, 0, 219.36232, 8.77449], ["Can", 473, 12, 26.65, 1, 26.75, 4.036697247706423, 217.05545, 8.68222], ["Keg", 58600, 1, 280.95, 0, 0, 0, 208.57804, 8.34312], ["Can", 355, 24, 44.75, 1, 42.95, 9.140369967355833, 204.07186, 8.16287], ["Can", 355, 48, 83.55, 0, 0, 0, 203.94973, 8.15799], ["Bottle", 355, 12, 21.3, 0, 0, 0, 200.0, 8.0], ["Can", 473, 6, 14.2, 0, 0, 0, 199.85915, 7.99437], ["Can", 473, 4, 9.8, 0, 0, 0, 193.06122, 7.72245], ["Can", 473, 1, 2.55, 0, 0, 0, 189.2, 7.568], ["Can", 355, 12, 23.349999999999998, 0, 0, 0, 182.44111, 7.29764]], "cnt": 12, "salePercent": 9.140369967355833, "value": 241.35977, "valAlc": 9.65439, "isSale": true, "price": 70.60000000000001}, {"brand": "Molson", "name": "Molson Canadian", "alcohol": 5.0, "pictureLink": "http://www.thebeerstore.ca/sites/default/files/styles/brand_hero/public/sbs/brand/18795%20Canadian%20TBS_GlasswareLineup.jpg?itok=FVhrAjzi", "pageLink": "http://www.thebeerstore.ca/beers/canadian", "rank": 25, "main": 0, "info": [["Bottle", 341, 36, 46.4, 0, 0, 0, 264.56897, 13.22845], ["Bottle", 341, 28, 40.150000000000006, 0, 0, 0, 237.80822, 11.89041], ["Bottle", 341, 24, 35.1, 0, 0, 0, 233.16239, 11.65812], ["Can", 710, 12, 37.9, 0, 0, 0, 224.80211, 11.24011], ["Can", 473, 24, 51.75, 0, 0, 0, 219.36232, 10.96812], ["Bottle", 341, 18, 28.15, 0, 0, 0, 218.04618, 10.90231], ["Bottle", 341, 30, 46.95, 0, 0, 0, 217.89137, 10.89457], ["Can", 473, 12, 26.15, 0, 0, 0, 217.05545, 10.85277], ["Can", 473, 6, 14.2, 1, 13.5, 8.965517241379317, 215.0, 10.75], ["Can", 355, 36, 60.7, 0, 0, 0, 210.54366, 10.52718], ["Can", 355, 48, 81.1, 0, 0, 0, 210.11097, 10.50555], ["Keg", 58600, 1, 280.95, 0, 0, 0, 208.57804, 10.4289], ["Can", 710, 2, 6.8500000000000005, 0, 0, 0, 207.29927, 10.36496], ["Can", 355, 24, 41.75, 0, 0, 0, 204.07186, 10.20359], ["Bottle", 710, 12, 41.75, 0, 0, 0, 204.07186, 10.20359], ["Can", 355, 30, 52.45, 0, 0, 0, 203.05052, 10.15253], ["Can", 710, 1, 3.5500000000000003, 0, 0, 0, 200.0, 10.0], ["Bottle", 341, 15, 26.0, 0, 0, 0, 196.73077, 9.83654], ["Can", 355, 15, 27.2, 0, 0, 0, 195.77206, 9.7886], ["Can", 473, 24, 58.75, 0, 0, 0, 193.22553, 9.66128], ["Can", 473, 4, 9.8, 0, 0, 0, 193.06122, 9.65306], ["Bottle", 341, 12, 21.3, 0, 0, 0, 192.11268, 9.60563], ["Can", 473, 1, 2.55, 0, 0, 0, 189.2, 9.46], ["Can", 355, 18, 34.6, 0, 0, 0, 184.68208, 9.2341], ["Can", 473, 4, 10.3, 0, 0, 0, 183.68932, 9.18447], ["Can", 473, 8, 21.1, 0, 0, 0, 179.33649, 8.96682], ["Keg", 20000, 1, 111.55000000000001, 0, 0, 0, 179.2918, 8.96459], ["Bottle", 341, 6, 11.65, 0, 0, 0, 175.62232, 8.78112], ["Can", 355, 6, 12.649999999999999, 0, 0, 0, 168.37945, 8.41897], ["Can", 355, 12, 26.349999999999998, 0, 0, 0, 161.66983, 8.08349]], "cnt": 30, "salePercent": 8.965517241379317, "value": 264.56897, "valAlc": 13.22845, "isSale": true, "price": 46.4}, {"brand": "Labatt", "name": "Bud Light", "alcohol": 4.0, "pictureLink": "http://www.thebeerstore.ca/sites/default/files/styles/brand_hero/public/sbs/brand/0574H.jpg?itok=5anlVfWi", "pageLink": "http://www.thebeerstore.ca/beers/bud-light", "rank": 26, "main": 0, "info": [["Bottle", 341, 36, 50.9, 0, 0, 0, 241.17878, 9.64715], ["Bottle", 341, 28, 40.150000000000006, 0, 0, 0, 237.80822, 9.51233], ["Bottle", 341, 24, 35.1, 0, 0, 0, 233.16239, 9.3265], ["Can", 473, 24, 51.75, 0, 0, 0, 219.36232, 8.77449], ["Can", 740, 12, 40.65, 0, 0, 0, 218.45018, 8.73801], ["Bottle", 341, 30, 46.95, 0, 0, 0, 217.89137, 8.71565], ["Can", 473, 6, 14.2, 1, 13.5, 8.965517241379317, 215.0, 8.6], ["Can", 355, 36, 60.7, 0, 0, 0, 210.54366, 8.42175], ["Can", 355, 48, 81.1, 0, 0, 0, 210.11097, 8.40444], ["Can", 473, 12, 27.15, 0, 0, 0, 209.06077, 8.36243], ["Keg", 58600, 1, 280.95, 0, 0, 0, 208.57804, 8.34312], ["Can", 740, 2, 7.25, 0, 0, 0, 204.13793, 8.16552], ["Can", 355, 30, 52.45, 0, 0, 0, 203.05052, 8.12202], ["Can", 740, 1, 3.7, 0, 0, 0, 200.0, 8.0], ["Bottle", 341, 15, 26.0, 0, 0, 0, 196.73077, 7.86923], ["Can", 473, 24, 58.75, 0, 0, 0, 193.22553, 7.72902], ["Bottle", 341, 12, 21.3, 0, 0, 0, 192.11268, 7.68451], ["Can", 473, 4, 9.950000000000001, 0, 0, 0, 190.15075, 7.60603], ["Can", 473, 1, 2.55, 0, 0, 0, 189.2, 7.568], ["Can", 473, 4, 10.05, 0, 0, 0, 188.25871, 7.53035], ["Can", 355, 18, 34.6, 0, 0, 0, 184.68208, 7.38728], ["Can", 355, 24, 46.3, 0, 0, 0, 184.01728, 7.36069], ["Can", 355, 15, 29.2, 0, 0, 0, 182.36301, 7.29452], ["Keg", 20000, 1, 111.55000000000001, 0, 0, 0, 179.2918, 7.17167], ["Bottle", 341, 6, 11.65, 0, 0, 0, 175.62232, 7.02489], ["Can", 355, 6, 12.649999999999999, 0, 0, 0, 168.37945, 6.73518], ["Can", 355, 12, 26.349999999999998, 0, 0, 0, 161.66983, 6.46679]], "cnt": 27, "salePercent": 8.965517241379317, "value": 241.17878, "valAlc": 9.64715, "isSale": true, "price": 50.9}, {"brand": "Diageo", "name": "Guinness Pub Draught", "alcohol": 4.0, "pictureLink": "http://www.thebeerstore.ca/sites/default/files/styles/brand_hero/public/brand/hero/2057-l.jpg?itok=AJfuQ7x1", "pageLink": "http://www.thebeerstore.ca/beers/guinness-pub-draught", "rank": 27, "main": 0, "info": [["Can", 500, 1, 2.95, 1, 2.7, 8.47457627118644, 188.67925, 7.54717], ["Can", 440, 24, 59.75, 0, 0, 0, 176.7364, 7.06946], ["Can", 500, 24, 68.75, 0, 0, 0, 174.54545, 6.98182], ["Can", 440, 12, 30.349999999999998, 0, 0, 0, 173.97035, 6.95881], ["Can", 440, 8, 21.55, 0, 0, 0, 163.34107, 6.53364], ["Can", 440, 4, 11.75, 0, 0, 0, 149.78723, 5.99149]], "cnt": 6, "salePercent": 8.47457627118644, "value": 188.67925, "valAlc": 7.54717, "isSale": true, "price": 2.95}, {"brand": "Thornbury Beverage Company", "name": "Thornbury Ladderrun Amber", "alcohol": 5.0, "pictureLink": "http://www.thebeerstore.ca/sites/default/files/styles/brand_hero/public/sbs/brand/1512H_0.png?itok=B-f3Et0X", "pageLink": "http://www.thebeerstore.ca/beers/king-brewery-vienna-lager", "rank": 28, "main": 0, "info": [["Can", 473, 24, 64.75, 0, 0, 0, 175.32046, 8.76602], ["Can", 473, 6, 16.65, 0, 0, 0, 170.45045, 8.52252], ["Can", 473, 1, 3.1, 1, 2.85, 8.064516129032262, 168.92857, 8.44643]], "cnt": 3, "salePercent": 8.064516129032262, "value": 175.32046, "valAlc": 8.76602, "isSale": true, "price": 64.75}, {"brand": "Labatt", "name": "Budweiser", "alcohol": 5.0, "pictureLink": "http://www.thebeerstore.ca/sites/default/files/styles/brand_hero/public/sbs/brand/0553%20H.jpg?itok=mBnVbF6d", "pageLink": "http://www.thebeerstore.ca/beers/budweiser", "rank": 29, "main": 0, "info": [["Bottle", 341, 36, 50.9, 0, 0, 0, 241.17878, 12.05894], ["Bottle", 341, 28, 40.150000000000006, 0, 0, 0, 237.80822, 11.89041], ["Bottle", 341, 24, 35.1, 0, 0, 0, 233.16239, 11.65812], ["Can", 473, 24, 51.75, 0, 0, 0, 219.36232, 10.96812], ["Can", 740, 12, 40.65, 0, 0, 0, 218.45018, 10.92251], ["Bottle", 341, 18, 28.15, 0, 0, 0, 218.04618, 10.90231], ["Bottle", 341, 30, 46.95, 0, 0, 0, 217.89137, 10.89457], ["Can", 355, 36, 60.7, 0, 0, 0, 210.54366, 10.52718], ["Can", 355, 48, 81.1, 0, 0, 0, 210.11097, 10.50555], ["Can", 473, 12, 27.15, 0, 0, 0, 209.06077, 10.45304], ["Keg", 58600, 1, 280.95, 0, 0, 0, 208.57804, 10.4289], ["Can", 473, 1, 2.55, 1, 2.35, 7.843137254901955, 205.65217, 10.28261], ["Can", 740, 2, 7.25, 0, 0, 0, 204.13793, 10.2069], ["Can", 355, 30, 52.45, 0, 0, 0, 203.05052, 10.15253], ["Can", 740, 1, 3.7, 0, 0, 0, 200.0, 10.0], ["Bottle", 341, 15, 26.0, 0, 0, 0, 196.73077, 9.83654], ["Can", 473, 6, 14.649999999999999, 0, 0, 0, 193.72014, 9.68601], ["Can", 473, 24, 58.75, 0, 0, 0, 193.22553, 9.66128], ["Bottle", 341, 12, 21.3, 0, 0, 0, 192.11268, 9.60563], ["Can", 473, 4, 9.950000000000001, 0, 0, 0, 190.15075, 9.50754], ["Bottle", 710, 12, 44.949999999999996, 0, 0, 0, 189.54394, 9.4772], ["Can", 473, 4, 10.05, 0, 0, 0, 188.25871, 9.41294], ["Can", 355, 18, 34.6, 0, 0, 0, 184.68208, 9.2341], ["Can", 355, 24, 46.3, 0, 0, 0, 184.01728, 9.20086], ["Can", 355, 15, 29.2, 0, 0, 0, 182.36301, 9.11815], ["Keg", 20000, 1, 111.55000000000001, 0, 0, 0, 179.2918, 8.96459], ["Bottle", 1183, 1, 6.6000000000000005, 0, 0, 0, 179.24242, 8.96212], ["Bottle", 341, 6, 11.65, 0, 0, 0, 175.62232, 8.78112], ["Bottle", 710, 1, 4.2, 0, 0, 0, 169.04762, 8.45238], ["Can", 355, 6, 12.649999999999999, 0, 0, 0, 168.37945, 8.41897], ["Can", 355, 12, 26.349999999999998, 0, 0, 0, 161.66983, 8.08349]], "cnt": 31, "salePercent": 7.843137254901955, "value": 241.17878, "valAlc": 12.05894, "isSale": true, "price": 50.9}, {"brand": "Creemore Springs Brewery", "name": "Creemore Collection", "alcohol": 5.0, "pictureLink": "http://www.thebeerstore.ca/sites/default/files/styles/brand_hero/public/sbs/brand/3579H.png?itok=Js5-x2kM", "pageLink": "http://www.thebeerstore.ca/beers/creemore-collection", "rank": 30, "main": 0, "info": [["Bottle", 341, 12, 26.95, 1, 24.95, 7.421150278293132, 172.29474, 8.61474]], "cnt": 1, "salePercent": 7.421150278293132, "value": 172.29474, "valAlc": 8.61474, "isSale": true, "price": 26.95}, {"brand": "Brick", "name": "Laker Lager", "alcohol": 5.0, "pictureLink": "http://www.thebeerstore.ca/sites/default/files/styles/brand_hero/public/sbs/brand/SBB0402-07_Laker_Lager_TBS_Graphic.jpg?itok=C6QHRzt3", "pageLink": "http://www.thebeerstore.ca/beers/laker-lager", "rank": 31, "main": 0, "info": [["Keg", 58600, 1, 180.95, 0, 0, 0, 323.84637, 16.19232], ["Bottle", 341, 24, 31.6, 1, 33.95, 7.2058823529411615, 259.39778, 12.96989], ["Keg", 20000, 1, 79.0, 0, 0, 0, 253.16456, 12.65823], ["Can", 473, 1, 1.95, 0, 0, 0, 248.94737, 12.44737], ["Can", 473, 6, 11.45, 0, 0, 0, 247.86026, 12.39301], ["Can", 473, 18, 34.35, 0, 0, 0, 247.86026, 12.39301], ["Can", 355, 30, 43.45, 0, 0, 0, 245.10932, 12.25547], ["Can", 473, 12, 23.349999999999998, 0, 0, 0, 243.08351, 12.15418], ["Can", 473, 24, 46.75, 0, 0, 0, 242.82353, 12.14118], ["Can", 355, 15, 22.2, 0, 0, 0, 239.86486, 11.99324], ["Bottle", 341, 18, 28.15, 0, 0, 0, 218.04618, 10.90231], ["Can", 355, 24, 39.75, 0, 0, 0, 214.33962, 10.71698], ["Can", 355, 18, 29.85, 0, 0, 0, 214.07035, 10.70352], ["Bottle", 341, 12, 19.3, 0, 0, 0, 212.02073, 10.60104], ["Bottle", 341, 6, 9.9, 0, 0, 0, 206.66667, 10.33333], ["Can", 355, 6, 10.45, 0, 0, 0, 203.82775, 10.19139], ["Can", 355, 12, 20.9, 0, 0, 0, 203.82775, 10.19139]], "cnt": 17, "salePercent": 7.2058823529411615, "value": 323.84637, "valAlc": 16.19232, "isSale": true, "price": 180.95}, {"brand": "Brick", "name": "Laker Ice", "alcohol": 5.0, "pictureLink": "http://www.thebeerstore.ca/sites/default/files/styles/brand_hero/public/sbs/brand/SBB0402-09_Laker_ICE_TBS_Graphic.jpg?itok=cRG5siB7", "pageLink": "http://www.thebeerstore.ca/beers/laker-ice", "rank": 32, "main": 0, "info": [["Bottle", 341, 24, 31.6, 1, 33.95, 7.2058823529411615, 259.39778, 12.96989], ["Can", 473, 1, 1.95, 0, 0, 0, 248.94737, 12.44737], ["Can", 473, 6, 11.45, 0, 0, 0, 247.86026, 12.39301], ["Can", 473, 18, 34.35, 0, 0, 0, 247.86026, 12.39301], ["Can", 355, 30, 43.45, 0, 0, 0, 245.10932, 12.25547], ["Can", 473, 12, 23.349999999999998, 0, 0, 0, 243.08351, 12.15418], ["Can", 473, 24, 46.75, 0, 0, 0, 242.82353, 12.14118], ["Can", 355, 15, 22.2, 0, 0, 0, 239.86486, 11.99324], ["Bottle", 341, 18, 28.15, 0, 0, 0, 218.04618, 10.90231], ["Bottle", 341, 12, 19.3, 0, 0, 0, 212.02073, 10.60104], ["Bottle", 341, 6, 9.9, 0, 0, 0, 206.66667, 10.33333]], "cnt": 11, "salePercent": 7.2058823529411615, "value": 259.39778, "valAlc": 12.96989, "isSale": true, "price": 31.6}, {"brand": "Brick", "name": "Laker Red", "alcohol": 5.0, "pictureLink": "http://www.thebeerstore.ca/sites/default/files/styles/brand_hero/public/sbs/brand/SBB0402-10_Laker_Red_TBS_Graphic.jpg?itok=hN7jBKwH", "pageLink": "http://www.thebeerstore.ca/beers/laker-red", "rank": 33, "main": 0, "info": [["Bottle", 341, 24, 31.6, 1, 33.95, 7.2058823529411615, 259.39778, 12.96989], ["Can", 473, 1, 1.95, 0, 0, 0, 248.94737, 12.44737], ["Can", 473, 6, 11.45, 0, 0, 0, 247.86026, 12.39301], ["Can", 473, 12, 23.349999999999998, 0, 0, 0, 243.08351, 12.15418], ["Can", 473, 24, 46.75, 0, 0, 0, 242.82353, 12.14118], ["Bottle", 341, 12, 19.3, 0, 0, 0, 212.02073, 10.60104]], "cnt": 6, "salePercent": 7.2058823529411615, "value": 259.39778, "valAlc": 12.96989, "isSale": true, "price": 31.6}, {"brand": "Sleeman Brewing", "name": "Maclays", "alcohol": 5.0, "pictureLink": "http://www.thebeerstore.ca/sites/default/files/styles/brand_hero/public/brand/hero/maclaysHERO.jpg?itok=aLiWQyOd", "pageLink": "http://www.thebeerstore.ca/beers/maclays", "rank": 34, "main": 0, "info": [["Bottle", 341, 24, 31.6, 1, 33.95, 7.2058823529411615, 259.39778, 12.96989], ["Can", 473, 1, 1.95, 0, 0, 0, 248.94737, 12.44737], ["Can", 473, 2, 3.8, 0, 0, 0, 248.94737, 12.44737], ["Can", 473, 8, 15.2, 0, 0, 0, 248.94737, 12.44737], ["Can", 473, 12, 22.799999999999997, 0, 0, 0, 248.94737, 12.44737], ["Can", 473, 18, 34.2, 0, 0, 0, 248.94737, 12.44737], ["Can", 473, 24, 45.599999999999994, 0, 0, 0, 248.94737, 12.44737], ["Can", 473, 4, 7.6499999999999995, 0, 0, 0, 247.32026, 12.36601], ["Can", 473, 6, 11.649999999999999, 0, 0, 0, 243.60515, 12.18026], ["Can", 355, 24, 37.75, 0, 0, 0, 225.69536, 11.28477], ["Bottle", 341, 12, 18.8, 1, 19.95, 6.25, 218.24, 10.912], ["Can", 355, 12, 20.95, 0, 0, 0, 203.34129, 10.16706]], "cnt": 12, "salePercent": 7.2058823529411615, "value": 259.39778, "valAlc": 12.96989, "isSale": true, "price": 31.6}, {"brand": "Sleeman Brewing", "name": "Blanche De Chambly", "alcohol": 5.0, "pictureLink": "http://www.thebeerstore.ca/sites/default/files/styles/brand_hero/public/brand/hero/blancheHERO_0.jpg?itok=GUBy3i4P", "pageLink": "http://www.thebeerstore.ca/beers/unibroue-blanche-dechambly", "rank": 35, "main": 0, "info": [["Keg", 30000, 1, 170.25, 0, 0, 0, 176.21145, 8.81057], ["Bottle", 341, 24, 48.15, 0, 0, 0, 169.96885, 8.49844], ["Bottle", 341, 12, 25.35, 0, 0, 0, 161.42012, 8.07101], ["Bottle", 341, 6, 14.3, 1, 13.3, 6.99300699300699, 161.10236, 8.05512]], "cnt": 4, "salePercent": 6.99300699300699, "value": 176.21145, "valAlc": 8.81057, "isSale": true, "price": 170.25}, {"brand": "Carlsberg International A/S", "name": "Carlsberg Lite", "alcohol": 4.0, "pictureLink": "http://www.thebeerstore.ca/sites/default/files/styles/brand_hero/public/sbs/brand/2130%20H.png?itok=VnZbLXaw", "pageLink": "http://www.thebeerstore.ca/beers/carlsberg-lite", "rank": 36, "main": 0, "info": [["Can", 500, 24, 45.599999999999994, 0, 0, 0, 263.15789, 10.52632], ["Can", 500, 1, 2.15, 0, 0, 0, 238.09524, 9.52381], ["Bottle", 330, 24, 43.550000000000004, 0, 0, 0, 181.85993, 7.2744], ["Bottle", 330, 12, 23.45, 0, 0, 0, 168.86994, 6.7548], ["Bottle", 330, 6, 12.6, 1, 12.9, 6.818181818181812, 160.97561, 6.43902]], "cnt": 5, "salePercent": 6.818181818181812, "value": 263.15789, "valAlc": 10.52632, "isSale": true, "price": 45.599999999999994}, {"brand": "Kompania Piwowarska S.A.", "name": "Lech Beer", "alcohol": 5.0, "pictureLink": "http://www.thebeerstore.ca/sites/default/files/styles/brand_hero/public/sbs/brand/2241H.jpg?itok=NkWN9-tH", "pageLink": "http://www.thebeerstore.ca/beers/lech-beer", "rank": 37, "main": 0, "info": [["Can", 500, 24, 46.9, 0, 0, 0, 255.86354, 12.79318], ["Can", 500, 1, 2.25, 1, 2.1, 6.666666666666665, 243.90244, 12.19512]], "cnt": 2, "salePercent": 6.666666666666665, "value": 255.86354, "valAlc": 12.79318, "isSale": true, "price": 46.9}, {"brand": "Sleeman Brewing", "name": "Sleeman Light", "alcohol": 4.0, "pictureLink": "http://www.thebeerstore.ca/sites/default/files/styles/brand_hero/public/brand/hero/SLT%20beer-glass-RGB.jpg?itok=APo_-Ruu", "pageLink": "http://www.thebeerstore.ca/beers/sleeman-light", "rank": 38, "main": 0, "info": [["Bottle", 341, 24, 34.6, 1, 36.95, 6.6216216216216095, 236.8741, 9.47496], ["Keg", 30000, 1, 146.25, 0, 0, 0, 205.12821, 8.20513], ["Can", 355, 24, 41.75, 0, 0, 0, 204.07186, 8.16287], ["Bottle", 341, 12, 22.3, 0, 0, 0, 183.49776, 7.33991], ["Can", 355, 12, 26.95, 0, 0, 0, 161.66983, 6.46679]], "cnt": 5, "salePercent": 6.6216216216216095, "value": 236.8741, "valAlc": 9.47496, "isSale": true, "price": 34.6}, {"brand": "Hop City Brewing Company", "name": "Hop City Barking Squirrel", "alcohol": 5.0, "pictureLink": "http://www.thebeerstore.ca/sites/default/files/styles/brand_hero/public/sbs/brand/7340H.png?itok=QnZ7qKdV", "pageLink": "http://www.thebeerstore.ca/beers/barking-squirrel-lager", "rank": 39, "main": 0, "info": [["Can", 473, 24, 63.75, 0, 0, 0, 178.07059, 8.90353], ["Bottle", 341, 24, 47.550000000000004, 0, 0, 0, 172.11356, 8.60568], ["Can", 473, 1, 3.05, 1, 2.85, 6.5573770491803245, 168.92857, 8.44643], ["Can", 473, 12, 33.9, 0, 0, 0, 167.43363, 8.37168], ["Bottle", 341, 12, 25.05, 0, 0, 0, 163.35329, 8.16766], ["Bottle", 341, 6, 13.65, 0, 0, 0, 149.89011, 7.49451]], "cnt": 6, "salePercent": 6.5573770491803245, "value": 178.07059, "valAlc": 8.90353, "isSale": true, "price": 63.75}, {"brand": "Goose Island Beer Company", "name": "Goose Island IPA ", "alcohol": 5.0, "pictureLink": "http://www.thebeerstore.ca/sites/default/files/styles/brand_hero/public/sbs/brand/GOOSE_IPA_PRODUCT.jpg?itok=n3vUDvi-", "pageLink": "http://www.thebeerstore.ca/beers/goose-island-ipa", "rank": 40, "main": 0, "info": [["Keg", 58600, 1, 315.25, 0, 0, 0, 185.88422, 9.29421], ["Bottle", 341, 24, 46.550000000000004, 0, 0, 0, 175.81096, 8.79055], ["Can", 473, 24, 64.75, 0, 0, 0, 175.32046, 8.76602], ["Can", 473, 12, 32.949999999999996, 0, 0, 0, 172.261, 8.61305], ["Can", 473, 1, 3.1, 1, 2.9, 6.451612903225811, 165.96491, 8.29825], ["Can", 473, 6, 17.2, 0, 0, 0, 165.0, 8.25], ["Bottle", 341, 12, 25.55, 0, 0, 0, 160.15656, 8.00783]], "cnt": 7, "salePercent": 6.451612903225811, "value": 185.88422, "valAlc": 9.29421, "isSale": true, "price": 315.25}, {"brand": "Lake Of Bays Brewing", "name": "Lake Of Bays Broken Axe", "alcohol": 4.0, "pictureLink": "http://www.thebeerstore.ca/sites/default/files/styles/brand_hero/public/sbs/brand/6412H.jpg?itok=cNmYKHHn", "pageLink": "http://www.thebeerstore.ca/beers/broken-axe-american-ale", "rank": 41, "main": 0, "info": [["Can", 473, 24, 66.0, 0, 0, 0, 172.0, 6.88], ["Can", 473, 12, 33.9, 0, 0, 0, 167.43363, 6.69735], ["Can", 473, 1, 3.1, 1, 2.9, 6.451612903225811, 165.96491, 6.6386], ["Can", 473, 6, 17.45, 0, 0, 0, 162.6361, 6.50544]], "cnt": 4, "salePercent": 6.451612903225811, "value": 172.0, "valAlc": 6.88, "isSale": true, "price": 66.0}, {"brand": "Nickel Brook Brewing Company", "name": "Nickel Brook Naughty Apa", "alcohol": 4.0, "pictureLink": "http://www.thebeerstore.ca/sites/default/files/styles/brand_hero/public/sbs/brand/6603%20H.png?itok=r_s3lwLK", "pageLink": "http://www.thebeerstore.ca/beers/naughty-neighbour-apa", "rank": 42, "main": 0, "info": [["Can", 473, 24, 62.8, 0, 0, 0, 180.76433, 7.23057], ["Can", 473, 1, 3.15, 1, 2.95, 6.349206349206337, 163.10345, 6.52414]], "cnt": 2, "salePercent": 6.349206349206337, "value": 180.76433, "valAlc": 7.23057, "isSale": true, "price": 62.8}, {"brand": "Craft Brew Alliance", "name": "Kona Big Wave Golden Ale", "alcohol": 4.0, "pictureLink": "http://www.thebeerstore.ca/sites/default/files/styles/brand_hero/public/sbs/brand/2395H.jpg?itok=nVviDlAW", "pageLink": "http://www.thebeerstore.ca/beers/kona-big-wave-golden-ale", "rank": 43, "main": 0, "info": [["Keg", 58600, 1, 321.95, 0, 0, 0, 182.01584, 7.28063], ["Bottle", 355, 24, 61.4, 1, 62.95, 5.0940438871473255, 140.71016, 5.62841], ["Bottle", 355, 6, 15.95, 0, 0, 0, 138.76221, 5.55049], ["Bottle", 355, 12, 30.75, 0, 0, 0, 138.53659, 5.54146]], "cnt": 4, "salePercent": 5.0940438871473255, "value": 182.01584, "valAlc": 7.28063, "isSale": true, "price": 321.95}, {"brand": "Dortmunder Actien Brewery", "name": "Dab Maibock", "alcohol": 7.0, "pictureLink": "http://www.thebeerstore.ca/sites/default/files/styles/brand_hero/public/brand/hero/TBS_DAB_MB_AND_GLASS.jpg?itok=Eq4TnN8h", "pageLink": "http://www.thebeerstore.ca/beers/dab-maibock", "rank": 44, "main": 0, "info": [["Can", 500, 1, 2.65, 1, 2.55, 3.7735849056603765, 200.0, 14.0]], "cnt": 1, "salePercent": 3.7735849056603765, "value": 200.0, "valAlc": 14.0, "isSale": true, "price": 2.65}, {"brand": "Sleeman Brewing", "name": "Pabst Blue Ribbon", "alcohol": 4.0, "pictureLink": "http://www.thebeerstore.ca/sites/default/files/styles/brand_hero/public/sbs/brand/3857H.png?itok=kH9weKwU", "pageLink": "http://www.thebeerstore.ca/beers/pabst-blue-ribbon", "rank": 45, "main": 0, "info": [["Bottle", 341, 30, 37.0, 0, 0, 0, 276.48649, 11.05946], ["Keg", 58600, 1, 217.5, 0, 0, 0, 269.42529, 10.77701], ["Bottle", 341, 24, 31.6, 0, 0, 0, 258.98734, 10.35949], ["Keg", 30000, 1, 121.75, 0, 0, 0, 246.40657, 9.85626], ["Can", 473, 6, 11.649999999999999, 0, 0, 0, 243.60515, 9.74421], ["Can", 355, 60, 88.0, 0, 0, 0, 242.04545, 9.68182], ["Can", 473, 24, 47.05, 0, 0, 0, 241.27524, 9.65101], ["Can", 355, 40, 59.0, 0, 0, 0, 240.67797, 9.62712], ["Can", 473, 12, 23.65, 0, 0, 0, 240.0, 9.6], ["Bottle", 341, 15, 21.45, 0, 0, 0, 238.46154, 9.53846], ["Can", 473, 8, 15.9, 0, 0, 0, 237.98742, 9.5195], ["Can", 355, 20, 30.0, 0, 0, 0, 236.66667, 9.46667], ["Can", 473, 4, 8.05, 0, 0, 0, 235.03106, 9.40124], ["Can", 473, 1, 2.1, 0, 0, 0, 230.73171, 9.22927], ["Can", 473, 2, 4.1000000000000005, 0, 0, 0, 230.73171, 9.22927], ["Can", 355, 24, 37.75, 0, 0, 0, 225.69536, 9.02781], ["Can", 355, 12, 20.95, 1, 21.5, 3.0162412993039567, 203.82775, 8.15311]], "cnt": 17, "salePercent": 3.0162412993039567, "value": 276.48649, "valAlc": 11.05946, "isSale": true, "price": 37.0}, {"brand": "Sleeman Brewing", "name": "Old Milwaukee", "alcohol": 4.0, "pictureLink": "http://www.thebeerstore.ca/sites/default/files/styles/brand_hero/public/sbs/brand/3852H.jpg?itok=arq4mAXA", "pageLink": "http://www.thebeerstore.ca/beers/old-milwaukee-0", "rank": 46, "main": 0, "info": [["Bottle", 341, 24, 31.6, 0, 0, 0, 258.98734, 10.35949], ["Can", 473, 6, 11.649999999999999, 0, 0, 0, 243.60515, 9.74421], ["Can", 473, 24, 47.05, 0, 0, 0, 241.27524, 9.65101], ["Can", 473, 18, 35.35, 0, 0, 0, 240.84866, 9.63395], ["Can", 473, 12, 23.65, 0, 0, 0, 240.0, 9.6], ["Can", 355, 30, 44.45, 0, 0, 0, 239.59505, 9.5838], ["Can", 355, 60, 89.0, 0, 0, 0, 239.32584, 9.57303], ["Can", 473, 4, 8.05, 0, 0, 0, 235.03106, 9.40124], ["Can", 473, 1, 2.1, 0, 0, 0, 230.73171, 9.22927], ["Can", 473, 2, 4.1000000000000005, 0, 0, 0, 230.73171, 9.22927], ["Can", 355, 45, 70.75, 0, 0, 0, 225.79505, 9.0318], ["Can", 355, 24, 37.75, 0, 0, 0, 225.69536, 9.02781], ["Can", 355, 15, 25.0, 0, 0, 0, 213.0, 8.52], ["Bottle", 341, 12, 19.3, 0, 0, 0, 212.02073, 8.48083], ["Can", 355, 6, 10.45, 0, 0, 0, 203.82775, 8.15311], ["Can", 355, 12, 20.95, 1, 21.5, 3.0162412993039567, 203.82775, 8.15311]], "cnt": 16, "salePercent": 3.0162412993039567, "value": 258.98734, "valAlc": 10.35949, "isSale": true, "price": 31.6}, {"brand": "Dortmunder Actien Brewery", "name": "Henninger Premium Lager", "alcohol": 5.0, "pictureLink": "http://www.thebeerstore.ca/sites/default/files/styles/brand_hero/public/sbs/brand/2339%20H.png?itok=laAWGjD0", "pageLink": "http://www.thebeerstore.ca/beers/henniger-premium-lager", "rank": 47, "main": 0, "info": [["Can", 500, 24, 46.9, 0, 0, 0, 255.86354, 12.79318], ["Can", 500, 6, 11.75, 0, 0, 0, 255.31915, 12.76596], ["Can", 500, 1, 2.1, 1, 2.05, 2.3809523809523947, 250.0, 12.5]], "cnt": 3, "salePercent": 2.3809523809523947, "value": 255.86354, "valAlc": 12.79318, "isSale": true, "price": 46.9}, {"brand": "Carlsberg International A/S", "name": "Tuborg Pilsner", "alcohol": 4.0, "pictureLink": "http://www.thebeerstore.ca/sites/default/files/styles/brand_hero/public/sbs/brand/2154H.png?itok=PP2B9hRH", "pageLink": "http://www.thebeerstore.ca/beers/tuborg-pilsner", "rank": 48, "main": 0, "info": [["Can", 500, 1, 2.2, 1, 2.15, 2.272727272727282, 238.09524, 9.52381], ["Can", 500, 24, 50.4, 0, 0, 0, 238.09524, 9.52381], ["Bottle", 330, 24, 43.45, 0, 0, 0, 182.27848, 7.29114], ["Bottle", 330, 12, 22.05, 0, 0, 0, 179.59184, 7.18367], ["Bottle", 330, 6, 12.200000000000001, 0, 0, 0, 162.29508, 6.4918]], "cnt": 5, "salePercent": 2.272727272727282, "value": 238.09524, "valAlc": 9.52381, "isSale": true, "price": 2.2}, {"brand": "Carlsberg International A/S", "name": "Holsten Festbock", "alcohol": 7.0, "pictureLink": "http://www.thebeerstore.ca/sites/default/files/styles/brand_hero/public/sbs/brand/holsten_festbock_large.jpg?itok=3eYrwUrm", "pageLink": "http://www.thebeerstore.ca/beers/holsten-festbock", "rank": 49, "main": 0, "info": [["Can", 500, 24, 59.8, 0, 0, 0, 200.6689, 14.04682], ["Can", 500, 1, 2.6, 1, 2.55, 1.9230769230769384, 200.0, 14.0]], "cnt": 2, "salePercent": 1.9230769230769384, "value": 200.6689, "valAlc": 14.04682, "isSale": true, "price": 59.8}, {"brand": "Les Brasseurs Sans Gluten", "name": "Glutenberg American Pale", "alcohol": 5.0, "pictureLink": "http://www.thebeerstore.ca/sites/default/files/styles/brand_hero/public/sbs/brand/2452%20H_0.png?itok=YEwdlFJf", "pageLink": "http://www.thebeerstore.ca/beers/glutenberg-american-pale", "rank": 50, "main": 0, "info": [["Can", 473, 24, 60.65, 0, 0, 0, 187.1723, 9.35862], ["Can", 473, 4, 11.05, 1, 10.85, 1.8099547511312264, 177.65258, 8.88263]], "cnt": 2, "salePercent": 1.8099547511312264, "value": 187.1723, "valAlc": 9.35862, "isSale": true, "price": 60.65}, {"brand": "Dortmunder Actien Brewery", "name": "Schofferhofer Radler", "alcohol": 2.0, "pictureLink": "http://www.thebeerstore.ca/sites/default/files/styles/brand_hero/public/sbs/brand/Schofferhofer%20GF-TBS%20glass%20-%20shot%20%233.jpg?itok=tR9BllbL", "pageLink": "http://www.thebeerstore.ca/beers/schofferhofer-grapefruit-radlr", "rank": 51, "main": 0, "info": [["Can", 500, 24, 53.75, 0, 0, 0, 223.25581, 4.46512], ["Can", 500, 6, 13.649999999999999, 0, 0, 0, 219.78022, 4.3956], ["Can", 500, 1, 2.85, 1, 2.8, 1.7543859649122862, 181.81818, 3.63636], ["Bottle", 330, 24, 46.6, 0, 0, 0, 169.95708, 3.39914], ["Bottle", 330, 12, 23.8, 0, 0, 0, 166.38655, 3.32773], ["Bottle", 330, 6, 13.4, 0, 0, 0, 147.76119, 2.95522]], "cnt": 6, "salePercent": 1.7543859649122862, "value": 223.25581, "valAlc": 4.46512, "isSale": true, "price": 53.75}, {"brand": "Fuller Turner Smith", "name": "Fullers Extra Spec Bitter", "alcohol": 5.0, "pictureLink": "http://www.thebeerstore.ca/sites/default/files/styles/brand_hero/public/brand/hero/TBS_ESB_AND_GLASS.jpg?itok=P-27JTyM", "pageLink": "http://www.thebeerstore.ca/beers/fullers-extra-special-bitter", "rank": 52, "main": 0, "info": [["Bottle", 500, 1, 3.4, 1, 3.35, 1.4705882352941124, 153.84615, 7.69231]], "cnt": 1, "salePercent": 1.4705882352941124, "value": 153.84615, "valAlc": 7.69231, "isSale": true, "price": 3.4}]
