[{"brand": "Molson", "name": "Export", "alcohol": 5.0, "pictureLink": "http://www.thebeerstore.ca/sites/default/files/styles/brand_hero/public/sbs/brand/EXPORT%20ARRAY_0.JPG?itok=e5tbJGPW", "pageLink": "http://www.thebeerstore.ca/beers/export", "rank": 0, "main": 0, "info": [["Bottle", 341, 24, 34.5, 1, 34.5, 6.630581867388374, 237.21739, 11.86087], ["Can", 473, 24, 48.5, 1, 48.5, 2.902902902902904, 234.06186, 11.70309], ["Can", 473, 12, 24.6, 1, 24.6, 3.529411764705881, 230.73171, 11.53659], ["Can", 473, 6, 12.35, 1, 12.35, 11.46953405017921, 229.79757, 11.48988], ["Can", 473, 4, 8.25, 1, 8.25, 13.157894736842103, 229.33333, 11.46667], ["Can", 473, 1, 2.45, 1, 2.1, 14.28571428571429, 225.2381, 11.2619], ["Keg", 58600, 1, 280.95, 0, 0, 0, 208.57804, 10.4289], ["Can", 355, 24, 40.95, 1, 40.95, 4.656577415599539, 208.05861, 10.40293], ["Bottle", 710, 12, 42.5, 0, 0, 0, 200.47059, 10.02353], ["Bottle", 341, 12, 20.5, 1, 20.5, 2.1479713603818618, 199.60976, 9.98049], ["Can", 355, 12, 21.5, 1, 21.5, 8.510638297872342, 198.13953, 9.90698]], "cnt": 11, "salePercent": 14.28571428571429, "value": 237.21739, "valAlc": 11.86087, "isSale": 1, "price": 34.5}, {"brand": "Double Trouble Brewing", "name": "Revenge Ginger Red IPA ", "alcohol": 6.2, "pictureLink": "http://www.thebeerstore.ca/sites/default/files/styles/brand_hero/public/sbs/brand/RG%20H_0.png?itok=3SCe5SA2", "pageLink": "http://www.thebeerstore.ca/beers/revenge-ginger-red-ipa", "rank": 1, "main": 0, "info": [["Can", 473, 24, 55.95, 1, 55.95, 12.509773260359658, 202.89544, 12.57952], ["Can", 473, 4, 10.5, 1, 10.5, 8.695652173913048, 180.19048, 11.17181], ["Can", 473, 1, 3.1, 0, 0, 0, 152.58065, 9.46]], "cnt": 3, "salePercent": 12.509773260359658, "value": 202.89544, "valAlc": 12.57952, "isSale": 1, "price": 55.95}, {"brand": "Pilsner Urquell A.S.", "name": "Pilsner Urquell", "alcohol": 4.4, "pictureLink": "http://www.thebeerstore.ca/sites/default/files/styles/brand_hero/public/brand/hero/grolsch.jpg?itok=-Z6VMuXq", "pageLink": "http://www.thebeerstore.ca/beers/pilsner-urquell", "rank": 2, "main": 0, "info": [["Can", 500, 24, 59.95, 0, 0, 0, 200.16681, 8.80734], ["Can", 500, 1, 2.9, 1, 2.55, 12.06896551724138, 196.07843, 8.62745], ["Can", 500, 4, 10.75, 0, 0, 0, 186.04651, 8.18605], ["Bottle", 330, 24, 48.95, 0, 0, 0, 161.79775, 7.1191], ["Bottle", 330, 12, 26.95, 0, 0, 0, 146.93878, 6.46531], ["Bottle", 330, 6, 14.15, 0, 0, 0, 139.92933, 6.15689]], "cnt": 6, "salePercent": 12.06896551724138, "value": 200.16681, "valAlc": 8.80734, "isSale": 1, "price": 59.95}, {"brand": "North American Craft", "name": "Tpb Freedom 35 Lager", "alcohol": 5.0, "pictureLink": "http://www.thebeerstore.ca/sites/default/files/styles/brand_hero/public/sbs/brand/3383H.png?itok=s8OBcxTm", "pageLink": "http://www.thebeerstore.ca/beers/tpb-freedom-35-lager", "rank": 3, "main": 0, "info": [["Can", 473, 24, 46.95, 1, 46.95, 11.3314447592068, 241.78914, 12.08946], ["Keg", 58600, 1, 272.95, 0, 0, 0, 214.69134, 10.73457], ["Can", 473, 12, 26.95, 1, 26.95, 6.908462867012089, 210.61224, 10.53061], ["Can", 473, 6, 13.95, 1, 13.95, 6.688963210702337, 203.44086, 10.17204], ["Can", 473, 1, 2.6, 0, 0, 0, 181.92308, 9.09615]], "cnt": 5, "salePercent": 11.3314447592068, "value": 241.78914, "valAlc": 12.08946, "isSale": 1, "price": 46.95}, {"brand": "Abe Erb Brewing Co", "name": "Abe Erb Das Spritzhaus", "alcohol": 4.7, "pictureLink": "http://www.thebeerstore.ca/sites/default/files/styles/brand_hero/public/sbs/brand/8031H.png?itok=73HLcBFs", "pageLink": "http://www.thebeerstore.ca/beers/abe-erb-das-spritzhaus", "rank": 4, "main": 0, "info": [["Can", 473, 1, 2.85, 1, 2.55, 10.526315789473696, 185.4902, 8.71804], ["Can", 473, 24, 61.5, 0, 0, 0, 184.58537, 8.67551], ["Can", 473, 12, 32.0, 0, 0, 0, 177.375, 8.33662], ["Can", 473, 6, 16.25, 0, 0, 0, 174.64615, 8.20837]], "cnt": 4, "salePercent": 10.526315789473696, "value": 185.4902, "valAlc": 8.71804, "isSale": 1, "price": 2.85}, {"brand": "Dortmunder Actien Brewery", "name": "Schofferhofer Radler", "alcohol": 2.5, "pictureLink": "http://www.thebeerstore.ca/sites/default/files/styles/brand_hero/public/sbs/brand/Schofferhofer%20GF-TBS%20glass%20-%20shot%20%233.jpg?itok=tR9BllbL", "pageLink": "http://www.thebeerstore.ca/beers/schofferhofer-grapefruit-radlr", "rank": 5, "main": 0, "info": [["Can", 500, 24, 54.95, 0, 0, 0, 218.38035, 5.45951], ["Can", 500, 6, 13.95, 0, 0, 0, 215.05376, 5.37634], ["Can", 500, 1, 2.85, 1, 2.55, 10.526315789473696, 196.07843, 4.90196], ["Bottle", 330, 24, 49.0, 0, 0, 0, 161.63265, 4.04082], ["Bottle", 330, 12, 25.0, 0, 0, 0, 158.4, 3.96], ["Bottle", 330, 6, 14.3, 0, 0, 0, 138.46154, 3.46154]], "cnt": 6, "salePercent": 10.526315789473696, "value": 218.38035, "valAlc": 5.45951, "isSale": 1, "price": 54.95}, {"brand": "Sleeman Brewing", "name": "Sapporo", "alcohol": 5.0, "pictureLink": "http://www.thebeerstore.ca/sites/default/files/styles/brand_hero/public/brand/hero/sapparoHERO.jpg?itok=TzpW2FbP", "pageLink": "http://www.thebeerstore.ca/beers/sapporo", "rank": 6, "main": 0, "info": [["Can", 500, 24, 58.95, 0, 0, 0, 203.56234, 10.17812], ["Can", 500, 12, 30.5, 0, 0, 0, 196.72131, 9.83607], ["Can", 500, 4, 10.25, 0, 0, 0, 195.12195, 9.7561], ["Keg", 30000, 1, 153.75, 0, 0, 0, 195.12195, 9.7561], ["Keg", 58600, 1, 300.5, 0, 0, 0, 195.00832, 9.75042], ["Can", 500, 6, 15.5, 0, 0, 0, 193.54839, 9.67742], ["Can", 650, 1, 3.45, 1, 3.45, 10.389610389610382, 188.4058, 9.42029], ["Can", 355, 24, 46.95, 0, 0, 0, 181.46965, 9.07348], ["Bottle", 341, 24, 46.5, 0, 0, 0, 176.0, 8.8], ["Can", 650, 12, 45.0, 0, 0, 0, 173.33333, 8.66667], ["Can", 650, 6, 22.8, 0, 0, 0, 171.05263, 8.55263], ["Can", 500, 1, 2.95, 0, 0, 0, 169.49153, 8.47458], ["Can", 355, 12, 26.0, 0, 0, 0, 163.84615, 8.19231], ["Bottle", 341, 12, 26.5, 0, 0, 0, 154.41509, 7.72075]], "cnt": 14, "salePercent": 10.389610389610382, "value": 203.56234, "valAlc": 10.17812, "isSale": 1, "price": 58.95}, {"brand": "Labatt", "name": "Budweiser", "alcohol": 5.0, "pictureLink": "http://www.thebeerstore.ca/sites/default/files/styles/brand_hero/public/sbs/brand/0553%20H.jpg?itok=mBnVbF6d", "pageLink": "http://www.thebeerstore.ca/beers/budweiser", "rank": 7, "main": 0, "info": [["Bottle", 341, 36, 54.5, 0, 0, 0, 225.24771, 11.26239], ["Bottle", 341, 28, 42.95, 0, 0, 0, 222.30501, 11.11525], ["Bottle", 341, 24, 37.5, 0, 0, 0, 218.24, 10.912], ["Can", 740, 12, 41.25, 0, 0, 0, 215.27273, 10.76364], ["Can", 473, 24, 52.95, 0, 0, 0, 214.39093, 10.71955], ["Keg", 58600, 1, 280.95, 0, 0, 0, 208.57804, 10.4289], ["Bottle", 341, 18, 29.95, 0, 0, 0, 204.94157, 10.24708], ["Bottle", 341, 30, 49.95, 0, 0, 0, 204.8048, 10.24024], ["Can", 473, 12, 27.75, 0, 0, 0, 204.54054, 10.22703], ["Can", 355, 36, 62.5, 0, 0, 0, 204.48, 10.224], ["Can", 355, 48, 83.5, 0, 0, 0, 204.07186, 10.20359], ["Can", 740, 2, 7.35, 0, 0, 0, 201.36054, 10.06803], ["Can", 355, 24, 42.95, 1, 42.95, 9.578947368421042, 198.3702, 9.91851], ["Can", 355, 30, 53.95, 0, 0, 0, 197.405, 9.87025], ["Can", 740, 1, 3.75, 0, 0, 0, 197.33333, 9.86667], ["Can", 473, 6, 14.5, 0, 0, 0, 195.72414, 9.78621], ["Can", 355, 15, 27.95, 1, 27.95, 6.6777963272120155, 190.51878, 9.52594], ["Can", 473, 24, 59.95, 0, 0, 0, 189.3578, 9.46789], ["Can", 473, 4, 10.15, 0, 0, 0, 186.40394, 9.3202], ["Bottle", 341, 6, 11.0, 1, 11.0, 10.204081632653061, 186.0, 9.3], ["Bottle", 341, 15, 27.5, 0, 0, 0, 186.0, 9.3], ["Can", 473, 1, 2.6, 1, 2.55, 1.9230769230769384, 185.4902, 9.27451], ["Bottle", 710, 12, 46.15, 0, 0, 0, 184.61538, 9.23077], ["Can", 473, 4, 10.25, 0, 0, 0, 184.58537, 9.22927], ["Bottle", 341, 12, 22.5, 0, 0, 0, 181.86667, 9.09333], ["Can", 355, 18, 35.5, 0, 0, 0, 180.0, 9.0], ["Keg", 20000, 1, 111.55000000000001, 0, 0, 0, 179.2918, 8.96459], ["Bottle", 1183, 1, 6.7, 0, 0, 0, 176.56716, 8.82836], ["Bottle", 710, 1, 4.3, 0, 0, 0, 165.11628, 8.25581], ["Can", 355, 6, 12.95, 0, 0, 0, 164.47876, 8.22394], ["Can", 355, 12, 26.95, 0, 0, 0, 158.0705, 7.90353]], "cnt": 31, "salePercent": 10.204081632653061, "value": 225.24771, "valAlc": 11.26239, "isSale": 1, "price": 54.5}, {"brand": "Palm Breweries Nv", "name": "Palm Amber Ale", "alcohol": 5.4, "pictureLink": "http://www.thebeerstore.ca/sites/default/files/styles/brand_hero/public/sbs/brand/2197H.png?itok=aRLuUsZX", "pageLink": "http://www.thebeerstore.ca/beers/palm-amber-ale", "rank": 8, "main": 0, "info": [["Bottle", 330, 12, 22.0, 1, 22.0, 10.204081632653061, 180.0, 9.72], ["Bottle", 330, 24, 44.95, 1, 44.95, 10.010010010010006, 176.19577, 9.51457], ["Bottle", 330, 6, 13.3, 1, 12.0, 9.774436090225569, 165.0, 8.91], ["Keg", 20000, 1, 129.4, 0, 0, 0, 154.55951, 8.34621]], "cnt": 4, "salePercent": 10.204081632653061, "value": 180.0, "valAlc": 9.72, "isSale": 1, "price": 22.0}, {"brand": "Labatt", "name": "Bud Light", "alcohol": 4.0, "pictureLink": "http://www.thebeerstore.ca/sites/default/files/styles/brand_hero/public/sbs/brand/0574H.jpg?itok=5anlVfWi", "pageLink": "http://www.thebeerstore.ca/beers/bud-light", "rank": 9, "main": 0, "info": [["Bottle", 341, 36, 54.5, 0, 0, 0, 225.24771, 9.00991], ["Bottle", 341, 28, 42.95, 0, 0, 0, 222.30501, 8.8922], ["Bottle", 341, 24, 37.5, 0, 0, 0, 218.24, 8.7296], ["Can", 740, 12, 41.25, 0, 0, 0, 215.27273, 8.61091], ["Can", 473, 24, 52.95, 0, 0, 0, 214.39093, 8.57564], ["Keg", 58600, 1, 280.95, 0, 0, 0, 208.57804, 8.34312], ["Bottle", 341, 30, 49.95, 0, 0, 0, 204.8048, 8.19219], ["Can", 473, 12, 27.75, 0, 0, 0, 204.54054, 8.18162], ["Can", 355, 36, 62.5, 0, 0, 0, 204.48, 8.1792], ["Can", 355, 48, 83.5, 0, 0, 0, 204.07186, 8.16287], ["Can", 740, 2, 7.35, 0, 0, 0, 201.36054, 8.05442], ["Can", 355, 24, 42.95, 1, 42.95, 9.578947368421042, 198.3702, 7.93481], ["Can", 355, 30, 53.95, 0, 0, 0, 197.405, 7.8962], ["Can", 740, 1, 3.75, 0, 0, 0, 197.33333, 7.89333], ["Can", 473, 6, 14.5, 0, 0, 0, 195.72414, 7.82897], ["Can", 355, 15, 27.95, 1, 27.95, 6.6777963272120155, 190.51878, 7.62075], ["Bottle", 341, 15, 27.5, 0, 0, 0, 186.0, 7.44], ["Can", 473, 1, 2.55, 0, 0, 0, 185.4902, 7.41961], ["Can", 473, 4, 10.25, 0, 0, 0, 184.58537, 7.38341], ["Bottle", 341, 12, 22.5, 0, 0, 0, 181.86667, 7.27467], ["Can", 355, 18, 35.5, 0, 0, 0, 180.0, 7.2], ["Keg", 20000, 1, 111.55000000000001, 0, 0, 0, 179.2918, 7.17167], ["Bottle", 341, 6, 12.25, 0, 0, 0, 167.02041, 6.68082], ["Can", 355, 6, 12.95, 0, 0, 0, 164.47876, 6.57915], ["Can", 355, 12, 26.95, 0, 0, 0, 158.0705, 6.32282]], "cnt": 25, "salePercent": 9.578947368421042, "value": 225.24771, "valAlc": 9.00991, "isSale": 1, "price": 54.5}, {"brand": "Molson", "name": "Coors Light", "alcohol": 4.0, "pictureLink": "http://www.thebeerstore.ca/sites/default/files/styles/brand_hero/public/sbs/brand/18795%20CoorsLight%20TBS_GlasswareLineup.jpg?itok=wI0NEtnH", "pageLink": "http://www.thebeerstore.ca/beers/coors-light", "rank": 10, "main": 0, "info": [["Bottle", 341, 36, 52.5, 0, 0, 0, 233.82857, 9.35314], ["Bottle", 341, 28, 42.95, 0, 0, 0, 222.30501, 8.8922], ["Can", 710, 12, 38.5, 0, 0, 0, 221.2987, 8.85195], ["Bottle", 341, 24, 37.5, 0, 0, 0, 218.24, 8.7296], ["Can", 473, 24, 52.95, 0, 0, 0, 214.39093, 8.57564], ["Can", 355, 36, 59.95, 0, 0, 0, 213.17765, 8.52711], ["Can", 473, 12, 26.75, 0, 0, 0, 212.18692, 8.48748], ["Keg", 58600, 1, 280.95, 0, 0, 0, 208.57804, 8.34312], ["Bottle", 341, 18, 29.95, 0, 0, 0, 204.94157, 8.19766], ["Bottle", 341, 30, 49.95, 0, 0, 0, 204.8048, 8.19219], ["Can", 710, 2, 6.95, 0, 0, 0, 204.31655, 8.17266], ["Can", 355, 48, 83.5, 0, 0, 0, 204.07186, 8.16287], ["Can", 355, 24, 42.95, 0, 0, 0, 198.3702, 7.93481], ["Bottle", 710, 12, 42.95, 0, 0, 0, 198.3702, 7.93481], ["Can", 355, 30, 53.95, 0, 0, 0, 197.405, 7.8962], ["Can", 710, 1, 3.6, 0, 0, 0, 197.22222, 7.88889], ["Can", 473, 6, 14.5, 0, 0, 0, 195.72414, 7.82897], ["Can", 355, 15, 27.95, 0, 0, 0, 190.51878, 7.62075], ["Can", 473, 24, 59.95, 0, 0, 0, 189.3578, 7.57431], ["Can", 473, 4, 10.0, 0, 0, 0, 189.2, 7.568], ["Bottle", 341, 15, 27.5, 0, 0, 0, 186.0, 7.44], ["Can", 473, 1, 2.55, 0, 0, 0, 185.4902, 7.41961], ["Bottle", 341, 12, 22.5, 0, 0, 0, 181.86667, 7.27467], ["Can", 355, 6, 11.75, 1, 11.75, 9.266409266409259, 181.2766, 7.25106], ["Can", 355, 18, 35.5, 0, 0, 0, 180.0, 7.2], ["Keg", 20000, 1, 111.55000000000001, 0, 0, 0, 179.2918, 7.17167], ["Can", 473, 8, 21.5, 0, 0, 0, 176.0, 7.04], ["Bottle", 341, 6, 12.25, 0, 0, 0, 167.02041, 6.68082], ["Can", 355, 12, 26.95, 0, 0, 0, 158.0705, 6.32282]], "cnt": 29, "salePercent": 9.266409266409259, "value": 233.82857, "valAlc": 9.35314, "isSale": 1, "price": 52.5}, {"brand": "Brick", "name": "Waterloo Dark", "alcohol": 5.0, "pictureLink": "http://www.thebeerstore.ca/sites/default/files/styles/brand_hero/public/sbs/brand/3066H_0.jpg?itok=aVDRcZNy", "pageLink": "http://www.thebeerstore.ca/beers/waterloo-dark", "rank": 11, "main": 0, "info": [["Keg", 58600, 1, 279.95, 0, 0, 0, 209.32309, 10.46615], ["Bottle", 341, 12, 19.95, 1, 19.95, 9.111617312072894, 205.11278, 10.25564], ["Bottle", 341, 24, 39.95, 0, 0, 0, 204.85607, 10.2428], ["Can", 473, 24, 56.95, 0, 0, 0, 199.33275, 9.96664], ["Can", 473, 12, 29.25, 0, 0, 0, 194.05128, 9.70256], ["Can", 473, 6, 14.95, 0, 0, 0, 189.83278, 9.49164], ["Can", 473, 18, 44.95, 0, 0, 0, 189.41046, 9.47052], ["Can", 473, 1, 2.5, 0, 0, 0, 189.2, 9.46], ["Keg", 20000, 1, 109.94999999999999, 0, 0, 0, 181.90086, 9.09504], ["Bottle", 341, 18, 35.95, 0, 0, 0, 170.73713, 8.53686], ["Bottle", 341, 6, 13.95, 0, 0, 0, 146.66667, 7.33333]], "cnt": 11, "salePercent": 9.111617312072894, "value": 209.32309, "valAlc": 10.46615, "isSale": 1, "price": 279.95}, {"brand": "Heineken Brouwerijen BV", "name": "Heineken", "alcohol": 5.0, "pictureLink": "http://www.thebeerstore.ca/sites/default/files/styles/brand_hero/public/brand/hero/heineken.jpg?itok=bORtwyPr", "pageLink": "http://www.thebeerstore.ca/beers/heineken-nv", "rank": 12, "main": 0, "info": [["Can", 500, 24, 61.95, 0, 0, 0, 193.7046, 9.68523], ["Bottle", 650, 12, 41.5, 0, 0, 0, 187.95181, 9.39759], ["Can", 500, 12, 31.95, 0, 0, 0, 187.79343, 9.38967], ["Can", 500, 8, 21.95, 0, 0, 0, 182.23235, 9.11162], ["Can", 500, 4, 11.25, 0, 0, 0, 177.77778, 8.88889], ["Can", 710, 1, 4.0, 0, 0, 0, 177.5, 8.875], ["Bottle", 330, 24, 45.95, 1, 45.95, 8.008008008008005, 172.36126, 8.61806], ["Bottle", 330, 18, 34.5, 1, 34.5, 7.9999999999999964, 172.17391, 8.6087], ["Can", 500, 1, 3.0, 0, 0, 0, 166.66667, 8.33333], ["Can", 5000, 2, 60.0, 0, 0, 0, 166.66667, 8.33333], ["Can", 330, 24, 47.95, 0, 0, 0, 165.17205, 8.2586], ["Bottle", 650, 1, 4.0, 0, 0, 0, 162.5, 8.125], ["Can", 5000, 1, 31.5, 0, 0, 0, 158.73016, 7.93651], ["Can", 330, 6, 12.5, 1, 12.5, 9.090909090909093, 158.4, 7.92], ["Keg", 50000, 1, 321.7, 0, 0, 0, 155.42431, 7.77122], ["Can", 330, 12, 25.95, 0, 0, 0, 152.60116, 7.63006], ["Bottle", 330, 12, 27.5, 0, 0, 0, 144.0, 7.2], ["Bottle", 330, 6, 14.5, 0, 0, 0, 136.55172, 6.82759]], "cnt": 18, "salePercent": 9.090909090909093, "value": 193.7046, "valAlc": 9.68523, "isSale": 1, "price": 61.95}, {"brand": "Wells And Young Brewing Compan", "name": "Wells IPA ", "alcohol": 5.0, "pictureLink": "http://www.thebeerstore.ca/sites/default/files/styles/brand_hero/public/sbs/brand/Wells%20IPA%20can.jpg?itok=VeuLs2eX", "pageLink": "http://www.thebeerstore.ca/beers/wells-ipa", "rank": 13, "main": 0, "info": [["Can", 500, 8, 16.15, 0, 0, 0, 247.67802, 12.3839], ["Can", 500, 4, 8.25, 0, 0, 0, 242.42424, 12.12121], ["Can", 500, 1, 2.3, 1, 2.1, 8.695652173913038, 238.09524, 11.90476], ["Can", 500, 24, 51.6, 0, 0, 0, 232.55814, 11.62791]], "cnt": 4, "salePercent": 8.695652173913038, "value": 247.67802, "valAlc": 12.3839, "isSale": 1, "price": 16.15}, {"brand": "Sleeman Brewing", "name": "Sleeman Clear 2.0", "alcohol": 4.0, "pictureLink": "http://www.thebeerstore.ca/sites/default/files/styles/brand_hero/public/brand/hero/SCR%20beer-glass-RGB.jpg?itok=ElyT8osw", "pageLink": "http://www.thebeerstore.ca/beers/sleeman-clear-20", "rank": 14, "main": 0, "info": [["Bottle", 341, 30, 43.95, 1, 43.95, 4.352557127312295, 232.76451, 9.31058], ["Bottle", 341, 24, 36.95, 0, 0, 0, 221.4885, 8.85954], ["Can", 473, 24, 52.95, 0, 0, 0, 214.39093, 8.57564], ["Can", 473, 6, 13.25, 1, 13.25, 8.62068965517241, 214.18868, 8.56755], ["Bottle", 341, 15, 23.95, 1, 23.95, 7.707129094412335, 213.56994, 8.5428], ["Keg", 30000, 1, 146.25, 0, 0, 0, 205.12821, 8.20513], ["Can", 473, 12, 27.75, 0, 0, 0, 204.54054, 8.18162], ["Can", 355, 24, 42.95, 0, 0, 0, 198.3702, 7.93481], ["Can", 355, 30, 53.95, 0, 0, 0, 197.405, 7.8962], ["Can", 355, 15, 27.95, 0, 0, 0, 190.51878, 7.62075], ["Can", 473, 4, 9.95, 0, 0, 0, 190.15075, 7.60603], ["Can", 473, 2, 5.0, 0, 0, 0, 189.2, 7.568], ["Can", 473, 1, 2.55, 0, 0, 0, 185.4902, 7.41961], ["Bottle", 341, 12, 23.95, 1, 23.95, 7.707129094412335, 170.85595, 6.83424], ["Can", 355, 12, 26.95, 0, 0, 0, 158.0705, 6.32282]], "cnt": 15, "salePercent": 8.62068965517241, "value": 232.76451, "valAlc": 9.31058, "isSale": 1, "price": 43.95}, {"brand": "Carlsberg International A/S", "name": "Tuborg Gold", "alcohol": 5.5, "pictureLink": "http://www.thebeerstore.ca/sites/default/files/styles/brand_hero/public/sbs/brand/2035H.png?itok=SlLRQMWE", "pageLink": "http://www.thebeerstore.ca/beers/tuborg-gold", "rank": 15, "main": 0, "info": [["Can", 500, 24, 50.25, 1, 50.25, 8.553230209281171, 238.80597, 13.13433], ["Can", 500, 1, 2.15, 0, 0, 0, 232.55814, 12.7907], ["Bottle", 330, 24, 46.05, 0, 0, 0, 171.98697, 9.45928], ["Bottle", 330, 12, 23.35, 0, 0, 0, 169.59315, 9.32762], ["Bottle", 330, 6, 12.8, 0, 0, 0, 154.6875, 8.50781]], "cnt": 5, "salePercent": 8.553230209281171, "value": 238.80597, "valAlc": 13.13433, "isSale": 1, "price": 50.25}, {"brand": "Carlsberg International A/S", "name": "Tuborg Pilsner", "alcohol": 4.6, "pictureLink": "http://www.thebeerstore.ca/sites/default/files/styles/brand_hero/public/sbs/brand/2154H.png?itok=PP2B9hRH", "pageLink": "http://www.thebeerstore.ca/beers/tuborg-pilsner", "rank": 16, "main": 0, "info": [["Can", 500, 24, 47.2, 1, 47.2, 8.52713178294573, 254.23729, 11.69492], ["Can", 500, 1, 2.15, 0, 0, 0, 232.55814, 10.69767], ["Bottle", 330, 24, 46.05, 0, 0, 0, 171.98697, 7.9114], ["Bottle", 330, 12, 23.35, 0, 0, 0, 169.59315, 7.80128], ["Bottle", 330, 6, 12.8, 0, 0, 0, 154.6875, 7.11562]], "cnt": 5, "salePercent": 8.52713178294573, "value": 254.23729, "valAlc": 11.69492, "isSale": 1, "price": 47.2}, {"brand": "Camerons Brewing Company", "name": "Camerons Cosmic Cream Ale", "alcohol": 5.0, "pictureLink": "http://www.thebeerstore.ca/sites/default/files/styles/brand_hero/public/sbs/brand/Cam_Cosmic_GW.jpg?itok=Hfkq_QBr", "pageLink": "http://www.thebeerstore.ca/beers/camerons-cream-ale", "rank": 17, "main": 0, "info": [["Keg", 58600, 1, 276.85, 0, 0, 0, 211.66697, 10.58335], ["Keg", 30000, 1, 152.55, 0, 0, 0, 196.65683, 9.83284], ["Can", 473, 24, 64.95, 0, 0, 0, 174.7806, 8.73903], ["Can", 473, 4, 10.95, 1, 10.95, 8.368200836820083, 172.78539, 8.63927], ["Can", 473, 6, 16.95, 0, 0, 0, 167.43363, 8.37168], ["Can", 473, 1, 3.05, 0, 0, 0, 155.08197, 7.7541]], "cnt": 6, "salePercent": 8.368200836820083, "value": 211.66697, "valAlc": 10.58335, "isSale": 1, "price": 276.85}, {"brand": "Molson", "name": "Rickards Red", "alcohol": 5.2, "pictureLink": "http://www.thebeerstore.ca/sites/default/files/styles/brand_hero/public/sbs/brand/RIC%20RED%20ARRAY_1.JPG?itok=u7kr5YX2", "pageLink": "http://www.thebeerstore.ca/beers/rickards-red", "rank": 18, "main": 0, "info": [["Keg", 58600, 1, 285.0, 0, 0, 0, 205.61404, 10.69193], ["Can", 473, 24, 57.95, 0, 0, 0, 195.89301, 10.18644], ["Can", 473, 12, 29.95, 0, 0, 0, 189.51586, 9.85482], ["Can", 473, 1, 2.7, 1, 2.5, 7.407407407407418, 189.2, 9.8384], ["Bottle", 341, 12, 21.95, 1, 21.95, 8.350730688935283, 186.42369, 9.69403], ["Bottle", 341, 24, 43.95, 0, 0, 0, 186.2116, 9.683], ["Can", 473, 6, 15.5, 0, 0, 0, 183.09677, 9.52103], ["Keg", 20000, 1, 109.94999999999999, 0, 0, 0, 181.90086, 9.45884], ["Can", 473, 4, 10.5, 0, 0, 0, 180.19048, 9.3699], ["Bottle", 341, 6, 13.25, 0, 0, 0, 154.41509, 8.02958]], "cnt": 10, "salePercent": 8.350730688935283, "value": 205.61404, "valAlc": 10.69193, "isSale": 1, "price": 285.0}, {"brand": "Ab Inbev", "name": "Stella Artois", "alcohol": 5.0, "pictureLink": "http://www.thebeerstore.ca/sites/default/files/styles/brand_hero/public/sbs/brand/TBS_Brand_Lockups_STA.jpg?itok=yB0uJW0J", "pageLink": "http://www.thebeerstore.ca/beers/stella-artois", "rank": 19, "main": 0, "info": [["Can", 500, 24, 61.95, 0, 0, 0, 193.7046, 9.68523], ["Can", 500, 12, 31.95, 0, 0, 0, 187.79343, 9.38967], ["Can", 500, 8, 21.95, 0, 0, 0, 182.23235, 9.11162], ["Can", 500, 1, 3.0, 1, 2.75, 8.333333333333337, 181.81818, 9.09091], ["Keg", 12000, 1, 67.25, 0, 0, 0, 178.43866, 8.92193], ["Can", 500, 4, 11.25, 0, 0, 0, 177.77778, 8.88889], ["Bottle", 330, 24, 46.95, 1, 46.95, 6.006006006006004, 168.6901, 8.4345], ["Can", 330, 24, 48.95, 0, 0, 0, 161.79775, 8.08989], ["Keg", 50000, 1, 329.15, 0, 0, 0, 151.90643, 7.59532], ["Can", 330, 12, 26.5, 0, 0, 0, 149.43396, 7.4717], ["Bottle", 330, 12, 27.5, 0, 0, 0, 144.0, 7.2], ["Can", 330, 6, 13.95, 0, 0, 0, 141.93548, 7.09677], ["Keg", 30000, 1, 215.5, 0, 0, 0, 139.21114, 6.96056], ["Bottle", 330, 6, 14.5, 0, 0, 0, 136.55172, 6.82759]], "cnt": 14, "salePercent": 8.333333333333337, "value": 193.7046, "valAlc": 9.68523, "isSale": 1, "price": 61.95}, {"brand": "Pilsner Urquell A.S.", "name": "Kozel", "alcohol": 4.9, "pictureLink": "http://www.thebeerstore.ca/sites/default/files/styles/brand_hero/public/sbs/brand/2136H.png?itok=LwPc52R2", "pageLink": "http://www.thebeerstore.ca/beers/kozel", "rank": 20, "main": 0, "info": [["Can", 500, 24, 44.1, 1, 44.1, 8.316008316008316, 272.10884, 13.33333], ["Can", 500, 4, 8.35, 0, 0, 0, 239.52096, 11.73653], ["Can", 500, 1, 2.25, 0, 0, 0, 222.22222, 10.88889]], "cnt": 3, "salePercent": 8.316008316008316, "value": 272.10884, "valAlc": 13.33333, "isSale": 1, "price": 44.1}, {"brand": "Double Trouble Brewing", "name": "Hops & Robbers IPA ", "alcohol": 5.7, "pictureLink": "http://www.thebeerstore.ca/sites/default/files/styles/brand_hero/public/sbs/brand/3375H.jpg?itok=cOZl1bLh", "pageLink": "http://www.thebeerstore.ca/beers/hops-robbers-ipa", "rank": 21, "main": 0, "info": [["Keg", 30000, 1, 137.8, 0, 0, 0, 217.70682, 12.40929], ["Can", 473, 24, 59.95, 1, 59.95, 7.698229407236335, 189.3578, 10.79339], ["Bottle", 355, 24, 45.95, 1, 45.95, 8.008008008008005, 185.41893, 10.56888], ["Can", 473, 4, 10.95, 1, 10.95, 5.194805194805207, 172.78539, 9.84877], ["Bottle", 355, 12, 24.95, 1, 24.95, 7.421150278293132, 170.74148, 9.73226], ["Bottle", 355, 6, 12.95, 1, 12.95, 7.168458781362008, 164.47876, 9.37529], ["Can", 473, 1, 3.0, 0, 0, 0, 157.66667, 8.987]], "cnt": 7, "salePercent": 8.008008008008005, "value": 217.70682, "valAlc": 12.40929, "isSale": 1, "price": 137.8}, {"brand": "Carlsberg International A/S", "name": "Holsten Premium Bier", "alcohol": 5.0, "pictureLink": "http://www.thebeerstore.ca/sites/default/files/styles/brand_hero/public/sbs/brand/2062%20H.png?itok=EvAYuiR3", "pageLink": "http://www.thebeerstore.ca/beers/holsten-premium-bier", "rank": 22, "main": 0, "info": [["Can", 500, 24, 47.5, 1, 47.5, 7.945736434108531, 252.63158, 12.63158], ["Can", 500, 1, 2.1, 0, 0, 0, 238.09524, 11.90476]], "cnt": 2, "salePercent": 7.945736434108531, "value": 252.63158, "valAlc": 12.63158, "isSale": 1, "price": 47.5}, {"brand": "Sleeman Brewing", "name": "Sleeman Orig. Draught", "alcohol": 5.0, "pictureLink": "http://www.thebeerstore.ca/sites/default/files/styles/brand_hero/public/brand/hero/SDR%20beer-glass-RGB.jpg?itok=enm4JnkZ", "pageLink": "http://www.thebeerstore.ca/beers/sleeman-original-draught", "rank": 23, "main": 0, "info": [["Bottle", 341, 30, 43.95, 1, 43.95, 4.352557127312295, 232.76451, 11.63823], ["Bottle", 341, 24, 36.95, 0, 0, 0, 221.4885, 11.07442], ["Can", 473, 24, 52.95, 0, 0, 0, 214.39093, 10.71955], ["Bottle", 341, 15, 23.95, 1, 23.95, 7.707129094412335, 213.56994, 10.6785], ["Keg", 58600, 1, 285.2, 0, 0, 0, 205.46985, 10.27349], ["Keg", 30000, 1, 146.25, 0, 0, 0, 205.12821, 10.25641], ["Can", 473, 12, 27.75, 0, 0, 0, 204.54054, 10.22703], ["Can", 355, 30, 53.95, 0, 0, 0, 197.405, 9.87025], ["Can", 473, 6, 14.5, 0, 0, 0, 195.72414, 9.78621], ["Can", 355, 15, 27.95, 0, 0, 0, 190.51878, 9.52594], ["Can", 473, 4, 9.95, 0, 0, 0, 190.15075, 9.50754], ["Can", 473, 2, 5.0, 0, 0, 0, 189.2, 9.46], ["Can", 473, 1, 2.55, 0, 0, 0, 185.4902, 9.27451], ["Bottle", 341, 12, 23.95, 1, 23.95, 7.707129094412335, 170.85595, 8.5428]], "cnt": 14, "salePercent": 7.707129094412335, "value": 232.76451, "valAlc": 11.63823, "isSale": 1, "price": 43.95}, {"brand": "Double Trouble Brewing", "name": "Hr Unfiltered", "alcohol": 4.6, "pictureLink": "http://www.thebeerstore.ca/sites/default/files/styles/brand_hero/public/sbs/brand/3379H.jpg?itok=L_FASQJ3", "pageLink": "http://www.thebeerstore.ca/beers/hr-unfiltered", "rank": 24, "main": 0, "info": [["Can", 473, 24, 59.95, 1, 59.95, 7.698229407236335, 189.3578, 8.71046], ["Can", 473, 4, 10.95, 1, 10.95, 5.194805194805207, 172.78539, 7.94813], ["Can", 473, 1, 2.95, 0, 0, 0, 160.33898, 7.37559]], "cnt": 3, "salePercent": 7.698229407236335, "value": 189.3578, "valAlc": 8.71046, "isSale": 1, "price": 59.95}, {"brand": "Carlsberg International A/S", "name": "Holsten Maibock", "alcohol": 7.0, "pictureLink": "http://www.thebeerstore.ca/sites/default/files/styles/brand_hero/public/sbs/brand/holsten_maibock_large.jpg?itok=aY5tc3lV", "pageLink": "http://www.thebeerstore.ca/beers/holsten-maibock", "rank": 25, "main": 0, "info": [["Can", 500, 24, 56.55, 1, 56.55, 7.3710073710073765, 212.20159, 14.85411], ["Can", 500, 1, 2.55, 0, 0, 0, 196.07843, 13.72549]], "cnt": 2, "salePercent": 7.3710073710073765, "value": 212.20159, "valAlc": 14.85411, "isSale": 1, "price": 56.55}, {"brand": "Molson", "name": "Carling Lager", "alcohol": 4.9, "pictureLink": "http://www.thebeerstore.ca/sites/default/files/styles/brand_hero/public/sbs/brand/TBS_Glassware%20Pairing_Carling%20Lager.jpg?itok=rZS1i92t", "pageLink": "http://www.thebeerstore.ca/beers/carling-lager", "rank": 26, "main": 0, "info": [["Can", 473, 6, 11.45, 1, 11.45, 7.287449392712553, 247.86026, 12.14515], ["Bottle", 341, 24, 34.5, 0, 0, 0, 237.21739, 11.62365], ["Can", 473, 24, 48.5, 0, 0, 0, 234.06186, 11.46903], ["Can", 473, 8, 16.4, 0, 0, 0, 230.73171, 11.30585], ["Can", 473, 12, 24.6, 0, 0, 0, 230.73171, 11.30585], ["Bottle", 341, 30, 44.55, 0, 0, 0, 229.62963, 11.25185], ["Can", 473, 4, 8.25, 0, 0, 0, 229.33333, 11.23733], ["Can", 473, 1, 2.1, 0, 0, 0, 225.2381, 11.03667], ["Can", 355, 60, 96.05, 0, 0, 0, 221.7595, 10.86622], ["Bottle", 341, 18, 27.95, 0, 0, 0, 219.60644, 10.76072], ["Can", 355, 48, 78.95, 0, 0, 0, 215.83281, 10.57581], ["Can", 355, 30, 50.0, 0, 0, 0, 213.0, 10.437], ["Can", 355, 24, 40.95, 0, 0, 0, 208.05861, 10.19487], ["Can", 355, 15, 26.5, 0, 0, 0, 200.9434, 9.84623], ["Bottle", 341, 12, 20.5, 0, 0, 0, 199.60976, 9.78088], ["Bottle", 341, 15, 25.65, 0, 0, 0, 199.4152, 9.77135], ["Can", 355, 6, 10.75, 0, 0, 0, 198.13953, 9.70884], ["Can", 355, 12, 21.5, 0, 0, 0, 198.13953, 9.70884], ["Bottle", 341, 6, 10.5, 0, 0, 0, 194.85714, 9.548]], "cnt": 19, "salePercent": 7.287449392712553, "value": 247.86026, "valAlc": 12.14515, "isSale": 1, "price": 11.45}, {"brand": "Mill Street Brewery", "name": "Mill St Original Organic", "alcohol": 4.2, "pictureLink": "http://www.thebeerstore.ca/sites/default/files/styles/brand_hero/public/brand/hero/mill%20st%20organic.jpg?itok=RRxpYqN8", "pageLink": "http://www.thebeerstore.ca/beers/mill-st-original-organic", "rank": 27, "main": 0, "info": [["Can", 473, 24, 66.5, 0, 0, 0, 170.70677, 7.16968], ["Bottle", 341, 24, 48.95, 0, 0, 0, 167.19101, 7.02202], ["Can", 473, 12, 34.5, 0, 0, 0, 164.52174, 6.90991], ["Can", 355, 12, 25.95, 1, 25.95, 7.155635062611809, 164.16185, 6.8948], ["Can", 355, 24, 52.95, 0, 0, 0, 160.90652, 6.75807], ["Can", 473, 1, 3.15, 1, 2.95, 6.349206349206337, 160.33898, 6.73424], ["Bottle", 341, 12, 26.5, 0, 0, 0, 154.41509, 6.48543], ["Bottle", 341, 6, 14.25, 0, 0, 0, 143.57895, 6.03032]], "cnt": 8, "salePercent": 7.155635062611809, "value": 170.70677, "valAlc": 7.16968, "isSale": 1, "price": 66.5}, {"brand": "Molson", "name": "Carling Ice", "alcohol": 5.5, "pictureLink": "http://www.thebeerstore.ca/sites/default/files/styles/brand_hero/public/sbs/brand/TBS_Glassware%20Pairing_Carling%20Ice_0.jpg?itok=W85VTFJr", "pageLink": "http://www.thebeerstore.ca/beers/carling-ice", "rank": 28, "main": 0, "info": [["Can", 473, 1, 2.1, 1, 1.95, 7.142857142857151, 242.5641, 13.34103], ["Bottle", 341, 24, 34.5, 0, 0, 0, 237.21739, 13.04696], ["Can", 473, 24, 48.5, 0, 0, 0, 234.06186, 12.8734], ["Can", 473, 8, 16.4, 0, 0, 0, 230.73171, 12.69024], ["Can", 473, 12, 24.6, 0, 0, 0, 230.73171, 12.69024], ["Can", 473, 6, 12.35, 0, 0, 0, 229.79757, 12.63887], ["Can", 355, 30, 50.0, 0, 0, 0, 213.0, 11.715], ["Can", 355, 24, 40.95, 0, 0, 0, 208.05861, 11.44322], ["Can", 355, 15, 26.5, 0, 0, 0, 200.9434, 11.05189], ["Bottle", 341, 12, 20.5, 0, 0, 0, 199.60976, 10.97854], ["Can", 355, 6, 10.75, 0, 0, 0, 198.13953, 10.89767], ["Can", 355, 12, 21.5, 0, 0, 0, 198.13953, 10.89767]], "cnt": 12, "salePercent": 7.142857142857151, "value": 242.5641, "valAlc": 13.34103, "isSale": 1, "price": 2.1}, {"brand": "Sleeman Brewing", "name": "Old Milwaukee Ice", "alcohol": 5.5, "pictureLink": "http://www.thebeerstore.ca/sites/default/files/styles/brand_hero/public/sbs/brand/3841H.jpg?itok=USLlWKsQ", "pageLink": "http://www.thebeerstore.ca/beers/old-milwaukee-ice", "rank": 29, "main": 0, "info": [["Can", 473, 1, 2.1, 1, 1.95, 7.142857142857151, 242.5641, 13.34103], ["Can", 473, 24, 48.25, 0, 0, 0, 235.27461, 12.9401], ["Can", 473, 18, 36.25, 0, 0, 0, 234.86897, 12.91779], ["Can", 473, 12, 24.25, 0, 0, 0, 234.06186, 12.8734], ["Can", 355, 60, 92.0, 0, 0, 0, 231.52174, 12.7337], ["Can", 473, 6, 12.35, 0, 0, 0, 229.79757, 12.63887], ["Can", 473, 2, 4.2, 0, 0, 0, 225.2381, 12.3881], ["Can", 355, 45, 73.0, 0, 0, 0, 218.83562, 12.03596], ["Can", 355, 30, 49.0, 0, 0, 0, 217.34694, 11.95408], ["Can", 355, 15, 25.75, 0, 0, 0, 206.79612, 11.37379]], "cnt": 10, "salePercent": 7.142857142857151, "value": 242.5641, "valAlc": 13.34103, "isSale": 1, "price": 2.1}, {"brand": "Carlsberg International A/S", "name": "Kronenbourg 1664 Blanc", "alcohol": 5.0, "pictureLink": "http://www.thebeerstore.ca/sites/default/files/styles/brand_hero/public/brand/hero/1664-blanc_0.jpg?itok=20l7XPvu", "pageLink": "http://www.thebeerstore.ca/beers/kronenbourg-1664-blanc", "rank": 30, "main": 0, "info": [["Can", 500, 24, 60.95, 0, 0, 0, 196.88269, 9.84413], ["Can", 500, 1, 2.85, 0, 0, 0, 175.4386, 8.77193], ["Can", 330, 24, 49.95, 0, 0, 0, 158.55856, 7.92793], ["Bottle", 330, 24, 49.95, 0, 0, 0, 158.55856, 7.92793], ["Bottle", 330, 6, 13.1, 1, 13.1, 7.092198581560282, 151.14504, 7.55725], ["Can", 330, 12, 27.5, 0, 0, 0, 144.0, 7.2], ["Bottle", 330, 12, 27.5, 0, 0, 0, 144.0, 7.2], ["Can", 330, 6, 14.1, 0, 0, 0, 140.42553, 7.02128]], "cnt": 8, "salePercent": 7.092198581560282, "value": 196.88269, "valAlc": 9.84413, "isSale": 1, "price": 60.95}, {"brand": "Mill Street Brewery", "name": "Mill St 100th Meridian", "alcohol": 5.0, "pictureLink": "http://www.thebeerstore.ca/sites/default/files/styles/brand_hero/public/sbs/brand/100M%20-%20GLASS_BOTTLE-01.jpg?itok=uvtCQKBZ", "pageLink": "http://www.thebeerstore.ca/beers/100th-meridian-organic-lager", "rank": 31, "main": 0, "info": [["Can", 473, 24, 66.5, 0, 0, 0, 170.70677, 8.53534], ["Bottle", 341, 24, 48.95, 0, 0, 0, 167.19101, 8.35955], ["Can", 473, 12, 34.5, 0, 0, 0, 164.52174, 8.22609], ["Can", 473, 4, 12.0, 0, 0, 0, 157.66667, 7.88333], ["Bottle", 341, 6, 13.25, 1, 13.25, 7.017543859649122, 154.41509, 7.72075], ["Bottle", 341, 12, 26.5, 0, 0, 0, 154.41509, 7.72075], ["Can", 473, 1, 3.15, 0, 0, 0, 150.15873, 7.50794]], "cnt": 7, "salePercent": 7.017543859649122, "value": 170.70677, "valAlc": 8.53534, "isSale": 1, "price": 66.5}, {"brand": "Camerons Brewing Company", "name": "Camerons Captains Log", "alcohol": 5.0, "pictureLink": "http://www.thebeerstore.ca/sites/default/files/styles/brand_hero/public/sbs/brand/Cam_CaptnLog_GW.jpg?itok=smwRscq4", "pageLink": "http://www.thebeerstore.ca/beers/camerons-lager", "rank": 32, "main": 0, "info": [["Keg", 58600, 1, 276.85, 0, 0, 0, 211.66697, 10.58335], ["Keg", 30000, 1, 152.55, 0, 0, 0, 196.65683, 9.83284], ["Can", 473, 24, 64.95, 0, 0, 0, 174.7806, 8.73903], ["Can", 473, 6, 16.95, 0, 0, 0, 167.43363, 8.37168], ["Can", 473, 1, 3.05, 1, 2.85, 6.5573770491803245, 165.96491, 8.29825], ["Can", 473, 4, 11.95, 0, 0, 0, 158.32636, 7.91632]], "cnt": 6, "salePercent": 6.5573770491803245, "value": 211.66697, "valAlc": 10.58335, "isSale": 1, "price": 276.85}, {"brand": "Lake Of Bays Brewing", "name": "Lake Of Bays Spark House", "alcohol": 5.0, "pictureLink": "http://www.thebeerstore.ca/sites/default/files/styles/brand_hero/public/sbs/brand/6414H_0.jpg?itok=vJBNAw2C", "pageLink": "http://www.thebeerstore.ca/beers/spark-house-red-ale", "rank": 33, "main": 0, "info": [["Can", 473, 24, 65.95, 0, 0, 0, 172.1304, 8.60652], ["Can", 473, 12, 33.95, 0, 0, 0, 167.18704, 8.35935], ["Can", 473, 1, 3.05, 1, 2.85, 6.5573770491803245, 165.96491, 8.29825], ["Can", 473, 6, 17.45, 0, 0, 0, 162.6361, 8.13181]], "cnt": 4, "salePercent": 6.5573770491803245, "value": 172.1304, "valAlc": 8.60652, "isSale": 1, "price": 65.95}, {"brand": "Camerons Brewing Company", "name": "Camerons Ambear Red Ale", "alcohol": 5.0, "pictureLink": "http://www.thebeerstore.ca/sites/default/files/styles/brand_hero/public/sbs/brand/Cam_Ambear_GW.jpg?itok=2drja55y", "pageLink": "http://www.thebeerstore.ca/beers/camerons-auburn-ale", "rank": 34, "main": 0, "info": [["Keg", 58600, 1, 276.85, 0, 0, 0, 211.66697, 10.58335], ["Keg", 30000, 1, 152.55, 0, 0, 0, 196.65683, 9.83284], ["Can", 473, 6, 15.95, 1, 15.95, 5.899705014749268, 177.93103, 8.89655], ["Can", 473, 24, 64.95, 0, 0, 0, 174.7806, 8.73903], ["Can", 473, 4, 11.95, 0, 0, 0, 158.32636, 7.91632], ["Can", 473, 1, 3.05, 0, 0, 0, 155.08197, 7.7541]], "cnt": 6, "salePercent": 5.899705014749268, "value": 211.66697, "valAlc": 10.58335, "isSale": 1, "price": 276.85}, {"brand": "Carlsberg International A/S", "name": "Holsten Festbock", "alcohol": 7.0, "pictureLink": "http://www.thebeerstore.ca/sites/default/files/styles/brand_hero/public/sbs/brand/holsten_festbock_large.jpg?itok=3eYrwUrm", "pageLink": "http://www.thebeerstore.ca/beers/holsten-festbock", "rank": 35, "main": 0, "info": [["Can", 500, 24, 57.6, 1, 57.6, 5.573770491803276, 208.33333, 14.58333], ["Can", 500, 1, 2.55, 0, 0, 0, 196.07843, 13.72549]], "cnt": 2, "salePercent": 5.573770491803276, "value": 208.33333, "valAlc": 14.58333, "isSale": 1, "price": 57.6}, {"brand": "Moosehead Breweries Limited", "name": "Moosehead Lager", "alcohol": 5.0, "pictureLink": "http://www.thebeerstore.ca/sites/default/files/styles/brand_hero/public/sbs/brand/7351H.png?itok=ztFLFoHk", "pageLink": "http://www.thebeerstore.ca/beers/moosehead-lager", "rank": 36, "main": 0, "info": [["Bottle", 341, 28, 43.5, 0, 0, 0, 219.49425, 10.97471], ["Bottle", 341, 24, 37.95, 1, 37.95, 5.006257822277849, 215.65217, 10.78261], ["Bottle", 341, 18, 31.2, 0, 0, 0, 196.73077, 9.83654], ["Can", 473, 24, 57.95, 0, 0, 0, 195.89301, 9.79465], ["Can", 473, 12, 29.95, 0, 0, 0, 189.51586, 9.47579], ["Can", 473, 4, 10.5, 0, 0, 0, 180.19048, 9.00952], ["Can", 473, 1, 2.7, 0, 0, 0, 175.18519, 8.75926], ["Can", 355, 24, 48.95, 0, 0, 0, 174.05516, 8.70276], ["Can", 355, 18, 38.55, 0, 0, 0, 165.75875, 8.28794], ["Bottle", 341, 12, 25.95, 0, 0, 0, 157.68786, 7.88439], ["Bottle", 341, 6, 14.05, 0, 0, 0, 145.62278, 7.28114], ["Can", 355, 12, 29.5, 0, 0, 0, 144.40678, 7.22034]], "cnt": 12, "salePercent": 5.006257822277849, "value": 219.49425, "valAlc": 10.97471, "isSale": 1, "price": 43.5}, {"brand": "Side Launch Brewing Company", "name": "Side Launch Dark Lager", "alcohol": 5.3, "pictureLink": "http://www.thebeerstore.ca/sites/default/files/styles/brand_hero/public/sbs/brand/8301%20H.jpg?itok=thxSujNf", "pageLink": "http://www.thebeerstore.ca/beers/side-launch-dark-lager", "rank": 37, "main": 0, "info": [["Can", 473, 12, 29.95, 0, 0, 0, 189.51586, 10.04434], ["Can", 473, 1, 3.0, 1, 2.85, 4.999999999999993, 165.96491, 8.79614]], "cnt": 2, "salePercent": 4.999999999999993, "value": 189.51586, "valAlc": 10.04434, "isSale": 1, "price": 29.95}, {"brand": "Ace Hill Beer Company", "name": "Ace Hill Vienna", "alcohol": 5.0, "pictureLink": "http://www.thebeerstore.ca/sites/default/files/styles/brand_hero/public/sbs/brand/4851H.jpg?itok=nn-Gib0c", "pageLink": "http://www.thebeerstore.ca/beers/ace-hill-vienna-lager", "rank": 38, "main": 0, "info": [["Keg", 30000, 1, 145.0, 0, 0, 0, 206.89655, 10.34483], ["Can", 473, 8, 21.0, 0, 0, 0, 180.19048, 9.00952], ["Can", 473, 24, 63.0, 1, 63.0, 4.545454545454541, 180.19048, 9.00952], ["Can", 473, 4, 11.6, 0, 0, 0, 163.10345, 8.15517], ["Can", 473, 1, 2.95, 0, 0, 0, 160.33898, 8.01695]], "cnt": 5, "salePercent": 4.545454545454541, "value": 206.89655, "valAlc": 10.34483, "isSale": 1, "price": 145.0}, {"brand": "Ace Hill Beer Company", "name": "Ace Hill Pilsner", "alcohol": 4.9, "pictureLink": "http://www.thebeerstore.ca/sites/default/files/styles/brand_hero/public/sbs/brand/4850H.png?itok=lYJvtg6d", "pageLink": "http://www.thebeerstore.ca/beers/ace-hill-pilsner", "rank": 39, "main": 0, "info": [["Keg", 30000, 1, 145.0, 0, 0, 0, 206.89655, 10.13793], ["Can", 473, 8, 21.0, 0, 0, 0, 180.19048, 8.82933], ["Can", 473, 24, 63.0, 1, 63.0, 4.545454545454541, 180.19048, 8.82933], ["Can", 473, 4, 11.6, 0, 0, 0, 163.10345, 7.99207], ["Can", 473, 1, 2.95, 0, 0, 0, 160.33898, 7.85661]], "cnt": 5, "salePercent": 4.545454545454541, "value": 206.89655, "valAlc": 10.13793, "isSale": 1, "price": 145.0}, {"brand": "Sierra Nevada Brewing Company", "name": "Sierra Nevada Pale Ale", "alcohol": 5.0, "pictureLink": "http://www.thebeerstore.ca/sites/default/files/styles/brand_hero/public/sbs/brand/2380H.png?itok=JOU9oDFZ", "pageLink": "http://www.thebeerstore.ca/beers/sierra-nevada-pale-ale", "rank": 40, "main": 0, "info": [["Keg", 58600, 1, 410.95, 1, 393.2, 4.319260250638768, 170.74592, 8.5373]], "cnt": 1, "salePercent": 4.319260250638768, "value": 170.74592, "valAlc": 8.5373, "isSale": 1, "price": 410.95}, {"brand": "Boston Beer Company", "name": "Twisted Tea", "alcohol": 5.0, "pictureLink": "http://www.thebeerstore.ca/sites/default/files/styles/brand_hero/public/sbs/brand/TT-Trio_TBS_322x344_0.jpg?itok=Pv2uEWye", "pageLink": "http://www.thebeerstore.ca/beers/twisted-tea", "rank": 41, "main": 0, "info": [["Can", 355, 24, 47.75, 0, 0, 0, 178.42932, 8.92147], ["Bottle", 355, 24, 47.75, 0, 0, 0, 178.42932, 8.92147], ["Can", 355, 12, 27.75, 0, 0, 0, 153.51351, 7.67568], ["Bottle", 355, 12, 27.75, 0, 0, 0, 153.51351, 7.67568], ["Bottle", 355, 6, 14.5, 1, 14.5, 3.9735099337748325, 146.89655, 7.34483]], "cnt": 5, "salePercent": 3.9735099337748325, "value": 178.42932, "valAlc": 8.92147, "isSale": 1, "price": 47.75}, {"brand": "Boston Beer Company", "name": "Twisted Tea Half & Half", "alcohol": 5.0, "pictureLink": "http://www.thebeerstore.ca/sites/default/files/styles/brand_hero/public/sbs/brand/TT_ON_TBS_Product_322x344-May-2016.jpg?itok=wk7uvl28", "pageLink": "http://www.thebeerstore.ca/beers/twisted-tea-half-half", "rank": 42, "main": 0, "info": [["Can", 355, 24, 47.75, 0, 0, 0, 178.42932, 8.92147], ["Bottle", 355, 24, 47.75, 0, 0, 0, 178.42932, 8.92147], ["Can", 355, 12, 27.75, 0, 0, 0, 153.51351, 7.67568], ["Bottle", 355, 12, 27.75, 0, 0, 0, 153.51351, 7.67568], ["Bottle", 355, 6, 14.5, 1, 14.5, 3.9735099337748325, 146.89655, 7.34483]], "cnt": 5, "salePercent": 3.9735099337748325, "value": 178.42932, "valAlc": 8.92147, "isSale": 1, "price": 47.75}, {"brand": "Sierra Nevada Brewing Company", "name": "Sierra Nevada Nooner", "alcohol": 5.2, "pictureLink": "http://www.thebeerstore.ca/sites/default/files/styles/brand_hero/public/sbs/brand/2436H.png?itok=PpP8bAsn", "pageLink": "http://www.thebeerstore.ca/beers/sierra-nevada-nooner", "rank": 43, "main": 0, "info": [["Keg", 30000, 1, 247.6, 1, 238.65, 3.6147011308562127, 159.02465, 8.26928]], "cnt": 1, "salePercent": 3.6147011308562127, "value": 159.02465, "valAlc": 8.26928, "isSale": 1, "price": 247.6}, {"brand": "San Miguel Brewing Intl Ltd", "name": "San Miguel Premium Lager", "alcohol": 4.8, "pictureLink": "http://www.thebeerstore.ca/sites/default/files/styles/brand_hero/public/sbs/brand/2294%20H.png?itok=afm8V7RP", "pageLink": "http://www.thebeerstore.ca/beers/san-miguel-premium-lager", "rank": 44, "main": 0, "info": [["Bottle", 330, 6, 13.9, 1, 13.4, 3.597122302158273, 147.76119, 7.09254]], "cnt": 1, "salePercent": 3.597122302158273, "value": 147.76119, "valAlc": 7.09254, "isSale": 1, "price": 13.9}, {"brand": "Muskoka Brewery", "name": "Muskoka Detour IPA ", "alcohol": 4.3, "pictureLink": "http://www.thebeerstore.ca/sites/default/files/styles/brand_hero/public/sbs/brand/Detour-322x344.jpg?itok=XmKZ5PbI", "pageLink": "http://www.thebeerstore.ca/beers/muskoka-detour-ipa", "rank": 45, "main": 0, "info": [["Can", 473, 24, 66.95, 1, 66.95, 1.471670345842535, 169.55937, 7.29105], ["Bottle", 341, 24, 51.95, 0, 0, 0, 157.53609, 6.77405], ["Can", 473, 8, 24.5, 1, 24.5, 1.8036072144288595, 154.44898, 6.64131], ["Can", 355, 12, 27.95, 1, 27.95, 3.4542314335060498, 152.41503, 6.55385], ["Can", 355, 24, 55.9, 1, 55.9, 3.4542314335060498, 152.41503, 6.55385], ["Bottle", 341, 12, 27.5, 1, 27.5, 1.610017889087656, 148.8, 6.3984], ["Can", 473, 1, 3.25, 0, 0, 0, 145.53846, 6.25815], ["Bottle", 341, 6, 14.4, 0, 0, 0, 142.08333, 6.10958]], "cnt": 8, "salePercent": 3.4542314335060498, "value": 169.55937, "valAlc": 7.29105, "isSale": 1, "price": 66.95}, {"brand": "Molson", "name": "Get2gether", "alcohol": 5.0, "pictureLink": "http://www.thebeerstore.ca/sites/default/files/styles/brand_hero/public/brand/hero/get2gether.jpg?itok=G6ECCxE4", "pageLink": "http://www.thebeerstore.ca/beers/get2gether", "rank": 46, "main": 0, "info": [["Bottle", 341, 24, 36.95, 1, 35.95, 2.706359945872805, 227.64951, 11.38248]], "cnt": 1, "salePercent": 2.706359945872805, "value": 227.64951, "valAlc": 11.38248, "isSale": 1, "price": 36.95}, {"brand": "Bavaria", "name": "Hollandia Pilsner", "alcohol": 5.0, "pictureLink": "http://www.thebeerstore.ca/sites/default/files/styles/brand_hero/public/sbs/brand/Hollandia-TBS%20glass%20-%20shot_0.jpg?itok=050yvYn1", "pageLink": "http://www.thebeerstore.ca/beers/hollandia-pilsner", "rank": 47, "main": 0, "info": [["Can", 440, 1, 2.0, 1, 1.95, 2.500000000000002, 225.64103, 11.28205], ["Can", 440, 24, 47.35, 0, 0, 0, 223.02006, 11.151], ["Can", 440, 6, 11.85, 0, 0, 0, 222.78481, 11.13924]], "cnt": 3, "salePercent": 2.500000000000002, "value": 225.64103, "valAlc": 11.28205, "isSale": 1, "price": 2.0}, {"brand": "Brick", "name": "Laker Red", "alcohol": 5.5, "pictureLink": "http://www.thebeerstore.ca/sites/default/files/styles/brand_hero/public/sbs/brand/SBB0402-10_Laker_Red_TBS_Graphic.jpg?itok=hN7jBKwH", "pageLink": "http://www.thebeerstore.ca/beers/laker-red", "rank": 48, "main": 0, "info": [["Can", 473, 1, 1.95, 0, 0, 0, 242.5641, 13.34103], ["Can", 473, 6, 11.7, 1, 11.7, 0.42553191489361764, 242.5641, 13.34103], ["Can", 473, 12, 23.4, 1, 23.4, 2.2964509394572064, 242.5641, 13.34103], ["Can", 473, 24, 46.8, 1, 46.8, 2.3983315954118956, 242.5641, 13.34103], ["Bottle", 341, 24, 34.5, 0, 0, 0, 237.21739, 13.04696], ["Bottle", 341, 12, 20.5, 0, 0, 0, 199.60976, 10.97854]], "cnt": 6, "salePercent": 2.3983315954118956, "value": 242.5641, "valAlc": 13.34103, "isSale": 1, "price": 1.95}, {"brand": "Bavaria", "name": "Hollandia Super Strong", "alcohol": 12.0, "pictureLink": "http://www.thebeerstore.ca/sites/default/files/styles/brand_hero/public/sbs/brand/2426%20H.png?itok=UGdWzzqX", "pageLink": "http://www.thebeerstore.ca/beers/hollandia-super-strong", "rank": 49, "main": 0, "info": [["Can", 500, 24, 101.15, 0, 0, 0, 118.63569, 14.23628], ["Can", 500, 1, 4.35, 1, 4.25, 2.298850574712641, 117.64706, 14.11765]], "cnt": 2, "salePercent": 2.298850574712641, "value": 118.63569, "valAlc": 14.23628, "isSale": 1, "price": 101.15}, {"brand": "Hop City Brewing Company", "name": "Hop City Barking Squirrel", "alcohol": 5.0, "pictureLink": "http://www.thebeerstore.ca/sites/default/files/styles/brand_hero/public/sbs/brand/7340H.png?itok=QnZ7qKdV", "pageLink": "http://www.thebeerstore.ca/beers/barking-squirrel-lager", "rank": 50, "main": 0, "info": [["Can", 473, 24, 64.95, 0, 0, 0, 174.7806, 8.73903], ["Bottle", 341, 24, 48.95, 1, 48.95, 2.0020020020020013, 167.19101, 8.35955], ["Can", 473, 1, 2.85, 0, 0, 0, 165.96491, 8.29825], ["Can", 473, 12, 34.5, 0, 0, 0, 164.52174, 8.22609], ["Bottle", 341, 12, 26.25, 0, 0, 0, 155.88571, 7.79429], ["Bottle", 341, 6, 14.25, 0, 0, 0, 143.57895, 7.17895]], "cnt": 6, "salePercent": 2.0020020020020013, "value": 174.7806, "valAlc": 8.73903, "isSale": 1, "price": 64.95}, {"brand": "Wellington County", "name": "Wellington Helles Lager", "alcohol": 4.5, "pictureLink": "http://www.thebeerstore.ca/sites/default/files/styles/brand_hero/public/sbs/brand/3353H.jpg?itok=GG8ZfQS_", "pageLink": "http://www.thebeerstore.ca/beers/wellington-helles-lager", "rank": 51, "main": 0, "info": [["Can", 355, 24, 45.25, 0, 0, 0, 188.28729, 8.47293], ["Can", 355, 6, 13.5, 1, 13.25, 1.851851851851849, 160.75472, 7.23396]], "cnt": 2, "salePercent": 1.851851851851849, "value": 188.28729, "valAlc": 8.47293, "isSale": 1, "price": 45.25}, {"brand": "Bavaria", "name": "Bavaria 8.6 Red", "alcohol": 7.9, "pictureLink": "http://www.thebeerstore.ca/sites/default/files/styles/brand_hero/public/brand/hero/2178-l.jpg?itok=pyHYNaKK", "pageLink": "http://www.thebeerstore.ca/beers/bavaria-86-red", "rank": 52, "main": 0, "info": [["Can", 500, 1, 3.0, 1, 2.95, 1.6666666666666607, 169.49153, 13.38983]], "cnt": 1, "salePercent": 1.6666666666666607, "value": 169.49153, "valAlc": 13.38983, "isSale": 1, "price": 3.0}, {"brand": "Muskoka Brewery", "name": "Muskoka Legendary Oddity", "alcohol": 7.1, "pictureLink": "http://www.thebeerstore.ca/sites/default/files/styles/brand_hero/public/sbs/brand/7014H.jpg?itok=-jSzlg0s", "pageLink": "http://www.thebeerstore.ca/beers/muskoka-legendary-oddity", "rank": 53, "main": 0, "info": [["Can", 473, 1, 3.5, 1, 3.45, 1.4285714285714235, 137.10145, 9.7342], ["Can", 473, 24, 82.8, 0, 0, 0, 137.10145, 9.7342]], "cnt": 2, "salePercent": 1.4285714285714235, "value": 137.10145, "valAlc": 9.7342, "isSale": 1, "price": 3.5}, {"brand": "Staatsbrauerei Weihenstephan", "name": "Weihenstephaner Dunkel", "alcohol": 5.3, "pictureLink": "http://www.thebeerstore.ca/sites/default/files/styles/brand_hero/public/sbs/brand/dunkel_weihenstephaner_large.jpg?itok=0lwWuxwl", "pageLink": "http://www.thebeerstore.ca/beers/dunkel-weihenstephaner", "rank": 54, "main": 0, "info": [["Keg", 30000, 1, 193.75, 0, 0, 0, 154.83871, 8.20645], ["Bottle", 500, 1, 3.75, 1, 3.7, 1.3333333333333308, 135.13514, 7.16216]], "cnt": 2, "salePercent": 1.3333333333333308, "value": 154.83871, "valAlc": 8.20645, "isSale": 1, "price": 193.75}, {"brand": "Carlsberg International A/S", "name": "Carlsberg", "alcohol": 5.0, "pictureLink": "http://www.thebeerstore.ca/sites/default/files/styles/brand_hero/public/sbs/brand/2129%20H.png?itok=gLxC8bhk", "pageLink": "http://www.thebeerstore.ca/beers/carlsberg", "rank": 55, "main": 0, "info": [["Can", 500, 1, 2.3, 0, 0, 0, 217.3913, 10.86957], ["Can", 500, 24, 55.95, 0, 0, 0, 214.47721, 10.72386], ["Can", 330, 24, 46.95, 0, 0, 0, 168.6901, 8.4345], ["Bottle", 330, 24, 46.95, 0, 0, 0, 168.6901, 8.4345], ["Bottle", 330, 12, 25.75, 0, 0, 0, 153.78641, 7.68932], ["Can", 330, 6, 12.95, 1, 12.95, 1.1450381679389388, 152.89575, 7.64479], ["Bottle", 330, 6, 12.95, 0, 0, 0, 152.89575, 7.64479]], "cnt": 7, "salePercent": 1.1450381679389388, "value": 217.3913, "valAlc": 10.86957, "isSale": 1, "price": 2.3}, {"brand": "Breuvages Octane", "name": "Four Loko Fruit Punch", "alcohol": 11.9, "pictureLink": "http://www.thebeerstore.ca/sites/default/files/styles/brand_hero/public/sbs/brand/2262%20H.jpg?itok=AzwekOYf", "pageLink": "http://www.thebeerstore.ca/beers/four-loko-fruit-punch", "rank": 56, "main": 0, "info": [["Can", 568, 12, 57.3, 0, 0, 0, 118.95288, 14.15539], ["Can", 568, 2, 9.75, 0, 0, 0, 116.51282, 13.86503], ["Can", 568, 1, 5.0, 1, 4.95, 1.0000000000000009, 114.74747, 13.65495]], "cnt": 3, "salePercent": 1.0000000000000009, "value": 118.95288, "valAlc": 14.15539, "isSale": 1, "price": 57.3}, {"brand": "Breuvages Octane", "name": "Four Loko Black Cherry", "alcohol": 11.9, "pictureLink": "http://www.thebeerstore.ca/sites/default/files/styles/brand_hero/public/sbs/brand/2299%20H.jpg?itok=zmgkxHXc", "pageLink": "http://www.thebeerstore.ca/beers/four-loko-black-cherry", "rank": 57, "main": 0, "info": [["Can", 568, 12, 57.3, 0, 0, 0, 118.95288, 14.15539], ["Can", 568, 2, 9.75, 0, 0, 0, 116.51282, 13.86503], ["Can", 568, 1, 5.0, 1, 4.95, 1.0000000000000009, 114.74747, 13.65495]], "cnt": 3, "salePercent": 1.0000000000000009, "value": 118.95288, "valAlc": 14.15539, "isSale": 1, "price": 57.3}, {"brand": "Breuvages Octane", "name": "Four Loko Grape", "alcohol": 11.9, "pictureLink": "http://www.thebeerstore.ca/sites/default/files/styles/brand_hero/public/sbs/brand/2297%20H.jpg?itok=nutrh9S7", "pageLink": "http://www.thebeerstore.ca/beers/four-loko-grape", "rank": 58, "main": 0, "info": [["Can", 568, 12, 57.3, 0, 0, 0, 118.95288, 14.15539], ["Can", 568, 2, 9.75, 0, 0, 0, 116.51282, 13.86503], ["Can", 568, 1, 5.0, 1, 4.95, 1.0000000000000009, 114.74747, 13.65495]], "cnt": 3, "salePercent": 1.0000000000000009, "value": 118.95288, "valAlc": 14.15539, "isSale": 1, "price": 57.3}, {"brand": "Breuvages Octane", "name": "Four Loko Peach", "alcohol": 11.9, "pictureLink": "http://www.thebeerstore.ca/sites/default/files/styles/brand_hero/public/sbs/brand/2298%20H.jpg?itok=Vqi6mtcB", "pageLink": "http://www.thebeerstore.ca/beers/four-loko-peach", "rank": 59, "main": 0, "info": [["Can", 568, 12, 57.3, 0, 0, 0, 118.95288, 14.15539], ["Can", 568, 2, 9.75, 0, 0, 0, 116.51282, 13.86503], ["Can", 568, 1, 5.0, 1, 4.95, 1.0000000000000009, 114.74747, 13.65495]], "cnt": 3, "salePercent": 1.0000000000000009, "value": 118.95288, "valAlc": 14.15539, "isSale": 1, "price": 57.3}, {"brand": "Breuvages Octane", "name": "Four Loko Lemonade", "alcohol": 11.9, "pictureLink": "http://www.thebeerstore.ca/sites/default/files/styles/brand_hero/public/sbs/brand/2261%20H.jpg?itok=8KPtU1fD", "pageLink": "http://www.thebeerstore.ca/beers/four-loko-lemonade", "rank": 60, "main": 0, "info": [["Can", 568, 12, 57.3, 0, 0, 0, 118.95288, 14.15539], ["Can", 568, 2, 9.75, 0, 0, 0, 116.51282, 13.86503], ["Can", 568, 1, 5.0, 1, 4.95, 1.0000000000000009, 114.74747, 13.65495]], "cnt": 3, "salePercent": 1.0000000000000009, "value": 118.95288, "valAlc": 14.15539, "isSale": 1, "price": 57.3}, {"brand": "Breuvages Octane", "name": "Four Loko Strawbrry Lemon", "alcohol": 11.9, "pictureLink": "http://www.thebeerstore.ca/sites/default/files/styles/brand_hero/public/sbs/brand/2403%20H.jpg?itok=NwOlVX3A", "pageLink": "http://www.thebeerstore.ca/beers/four-loko-strawberry-lemonade", "rank": 61, "main": 0, "info": [["Can", 568, 12, 57.3, 0, 0, 0, 118.95288, 14.15539], ["Can", 568, 2, 9.75, 0, 0, 0, 116.51282, 13.86503], ["Can", 568, 1, 5.0, 1, 4.95, 1.0000000000000009, 114.74747, 13.65495]], "cnt": 3, "salePercent": 1.0000000000000009, "value": 118.95288, "valAlc": 14.15539, "isSale": 1, "price": 57.3}, {"brand": "Breuvages Octane", "name": "Four Loko Watermelon", "alcohol": 11.9, "pictureLink": "http://www.thebeerstore.ca/sites/default/files/styles/brand_hero/public/sbs/brand/2263%20H.jpg?itok=0TNHXHtC", "pageLink": "http://www.thebeerstore.ca/beers/four-loko-watermelon", "rank": 62, "main": 0, "info": [["Can", 568, 12, 57.3, 0, 0, 0, 118.95288, 14.15539], ["Can", 568, 2, 9.75, 0, 0, 0, 116.51282, 13.86503], ["Can", 568, 1, 5.0, 1, 4.95, 1.0000000000000009, 114.74747, 13.65495]], "cnt": 3, "salePercent": 1.0000000000000009, "value": 118.95288, "valAlc": 14.15539, "isSale": 1, "price": 57.3}, {"brand": "James Ready Brewing Company", "name": "James Ready Ice 6.0", "alcohol": 6.0, "pictureLink": "http://www.thebeerstore.ca/sites/default/files/styles/brand_hero/public/brand/hero/JamesReady-Can_021714.jpg?itok=dO4fGJa5", "pageLink": "http://www.thebeerstore.ca/beers/james-ready-ice-60", "rank": 63, "main": 0, "info": [["Can", 473, 24, 50.45, 1, 50.45, 0.9813542688910659, 225.01487, 13.50089], ["Can", 473, 12, 25.25, 1, 25.25, 0.19762845849802257, 224.79208, 13.48752], ["Can", 473, 6, 12.65, 0, 0, 0, 224.34783, 13.46087], ["Can", 473, 1, 2.15, 0, 0, 0, 220.0, 13.2]], "cnt": 4, "salePercent": 0.9813542688910659, "value": 225.01487, "valAlc": 13.50089, "isSale": 1, "price": 50.45}]